{"id":"d5a2eb42-8065-4174-ab79-0a6fa820e35e","name":"Browns","market":"Cleveland","alias":"CLE","sr_id":"sr:competitor:4417","franchise":{"id":"419d8ce3-3352-429e-a8ba-0e89891fca3e","name":"Browns","alias":"CLE","references":[{"id":"36","origin":"gsis"}]},"venue":{"id":"90c38d91-3774-4f5d-82ca-1c806828219f","name":"FirstEnergy Stadium","city":"Cleveland","state":"OH","country":"USA","zip":"44114","address":"100 Alfred Lerner Way","capacity":67895,"surface":"turf","roof_type":"outdoor","sr_id":"sr:venue:8177","location":{"lat":"41.506054","lng":"-81.700004"}},"division":{"id":"eb60da78-4eb5-4184-971e-2c5cd4ab4988","name":"AFC North","alias":"AFC_NORTH"},"conference":{"id":"1bdefe12-6cb2-4d6a-b208-b04602ae79c3","name":"AFC","alias":"AFC"},"references":[{"id":"CLV","origin":"gsis"}],"coaches":[{"id":"556e3f71-6120-49a4-a97f-9b139afc6bf9","full_name":"Alex Van Pelt","first_name":"Alex","last_name":"Van Pelt","position":"Offensive Coordinator"},{"id":"c232fbca-e44b-4523-90eb-268e4bbb5d5f","full_name":"Joe Woods","first_name":"Joe","last_name":"Woods","position":"Defensive Coordinator"},{"id":"e266a725-2c3d-4222-be78-19bc78e5b85e","full_name":"Kevin Stefanski","first_name":"Kevin","last_name":"Stefanski","position":"Head Coach"}],"team_colors":[{"type":"secondary","hex_color":"#ff3c00","alpha":0.0,"rgb_color":{"red":255,"green":60,"blue":0}},{"type":"primary","hex_color":"#311d00","alpha":0.0,"rgb_color":{"red":49,"green":29,"blue":0}}],"players":[{"id":"013477a2-0271-4441-a0af-9bc25924a2f6","name":"Stephen Carlson","jersey":"89","last_name":"Carlson","first_name":"Stephen","abbr_name":"S.Carlson","preferred_name":"Stephen","birth_date":"1996-12-12","weight":240.0,"height":76,"position":"TE","birth_place":"Jamestown, NY, USA","high_school":"Jamestown (NY)","college":"Princeton","college_conf":"Ivy League","rookie_year":2019,"status":"A01","sr_id":"sr:player:1190320","references":[{"id":"00-0035039","origin":"gsis"},{"id":"48136","origin":"nflx"}]},{"id":"017375c1-6522-43a8-b099-3ea0d15c95c9","name":"Drake Dorbeck","jersey":"68","last_name":"Dorbeck","first_name":"Drake","abbr_name":"D.Dorbeck","preferred_name":"Drake","birth_date":"1996-10-07","weight":320.0,"height":78,"position":"T","birth_place":"Vicksburg, MS, USA","high_school":"St. Aloysius (MS)","college":"Southern Mississippi","college_conf":"Conference USA","rookie_year":2020,"status":"R62","sr_id":"sr:player:1205824","references":[{"id":"00-0036113","origin":"gsis"},{"id":"53017","origin":"nflx"}]},{"id":"0207678d-d682-4916-ba20-74a218d5b6b1","name":"Joel Bitonio","jersey":"75","last_name":"Bitonio","first_name":"Joel","abbr_name":"J.Bitonio","preferred_name":"Joel","birth_date":"1991-10-11","weight":320.0,"height":76,"position":"G","birth_place":"San Pedro, CA, USA","high_school":"Long Beach Wilson (CA)","college":"Nevada","college_conf":"Mountain West Conference","rookie_year":2014,"status":"A01","sr_id":"sr:player:831487","draft":{"year":2014,"round":2,"number":35,"team":{"id":"d5a2eb42-8065-4174-ab79-0a6fa820e35e","name":"Browns","market":"Cleveland","alias":"CLE","sr_id":"sr:competitor:4417"}},"references":[{"id":"41264","origin":"nflx"},{"id":"00-0031426","origin":"gsis"}]},{"id":"06e41dc1-d5dc-4bdc-8fc3-e0d7c3a99ac4","name":"Jarvis Landry","jersey":"80","last_name":"Landry","first_name":"Jarvis","abbr_name":"J.Landry","preferred_name":"Jarvis","birth_date":"1992-11-28","weight":196.0,"height":71,"position":"WR","birth_place":"Metairie, LA, USA","high_school":"Lutcher (LA)","college":"Louisiana State","college_conf":"Southeastern Conference","rookie_year":2014,"status":"A01","sr_id":"sr:player:828581","draft":{"year":2014,"round":2,"number":63,"team":{"id":"4809ecb0-abd3-451d-9c4a-92a90b83ca06","name":"Dolphins","market":"Miami","alias":"MIA","sr_id":"sr:competitor:4287"}},"references":[{"id":"00-0031382","origin":"gsis"},{"id":"41292","origin":"nflx"}]},{"id":"072ec285-1430-48d4-9342-5a1b9af527f3","name":"Adrian Clayborn","jersey":"94","last_name":"Clayborn","first_name":"Adrian","abbr_name":"A.Clayborn","preferred_name":"Adrian","birth_date":"1988-07-06","weight":280.0,"height":75,"position":"DE","birth_place":"St. Louis, MO, USA","high_school":"Webster Groves (MO)","college":"Iowa","college_conf":"Big Ten Conference","rookie_year":2011,"status":"A01","sr_id":"sr:player:830421","draft":{"year":2011,"round":1,"number":20,"team":{"id":"4254d319-1bc7-4f81-b4ab-b5e6f3402b69","name":"Buccaneers","market":"Tampa Bay","alias":"TB","sr_id":"sr:competitor:4388"}},"references":[{"id":"37093","origin":"nflx"},{"id":"00-0027958","origin":"gsis"}]},{"id":"0790a8d6-5316-4204-91a6-8508ca48973b","name":"Mack Wilson","jersey":"51","last_name":"Wilson","first_name":"Mack","abbr_name":"M.Wilson","preferred_name":"Mack","birth_date":"1998-02-14","weight":240.0,"height":73,"position":"OLB","birth_place":"Montgomery, AL, USA","high_school":"Carver (AL)","college":"Alabama","college_conf":"Southeastern Conference","rookie_year":2019,"status":"A01","sr_id":"sr:player:1217138","draft":{"year":2019,"round":5,"number":155,"team":{"id":"d5a2eb42-8065-4174-ab79-0a6fa820e35e","name":"Browns","market":"Cleveland","alias":"CLE","sr_id":"sr:competitor:4417"}},"references":[{"id":"00-0035144","origin":"gsis"},{"id":"47938","origin":"nflx"}]},{"id":"07dbf3ec-0d6b-42f1-a2e8-7dd437339417","name":"A.J. Green","jersey":"38","last_name":"Green","first_name":"A.J.","abbr_name":"A.Green","preferred_name":"A.J.","birth_date":"1998-06-09","weight":185.0,"height":73,"position":"CB","birth_place":"DeSoto, TX, USA","high_school":"DeSoto (TX)","college":"Oklahoma State","college_conf":"Big Twelve Conference","rookie_year":2020,"status":"A01","sr_id":"sr:player:1224176","references":[{"id":"53018","origin":"nflx"},{"id":"00-0036114","origin":"gsis"}]},{"id":"0a63f97d-9cc2-44d0-b65a-ac2e78db73f9","name":"Tavierre Thomas","jersey":"20","last_name":"Thomas","first_name":"Tavierre","abbr_name":"T.Thomas","preferred_name":"Tavierre","birth_date":"1996-03-11","weight":205.0,"height":70,"position":"CB","birth_place":"Detroit, MI, USA","high_school":"Allen Academy (MI)","college":"Ferris State","college_conf":"Great Lakes Intercollegiate Athletic Conference","rookie_year":2018,"status":"A01","sr_id":"sr:player:1475834","references":[{"id":"46672","origin":"nflx"},{"id":"00-0034488","origin":"gsis"}]},{"id":"0e7d7ddc-6515-4034-8857-5ab9da6b7c25","name":"Jack Conklin","jersey":"78","last_name":"Conklin","first_name":"Jack","abbr_name":"J.Conklin","preferred_name":"Jack","birth_date":"1994-08-17","weight":308.0,"height":78,"position":"T","birth_place":"Plainwell, MI, USA","high_school":"Plainwell (MI)","college":"Michigan State","college_conf":"Big Ten Conference","rookie_year":2016,"status":"A01","sr_id":"sr:player:986905","draft":{"year":2016,"round":1,"number":8,"team":{"id":"d26a1ca5-722d-4274-8f97-c92e49c96315","name":"Titans","market":"Tennessee","alias":"TEN","sr_id":"sr:competitor:367364"}},"references":[{"id":"43297","origin":"nflx"},{"id":"00-0033057","origin":"gsis"}]},{"id":"0ef0d0ca-2d2d-455b-ab63-a20c01303e37","name":"Kareem Hunt","jersey":"27","last_name":"Hunt","first_name":"Kareem","abbr_name":"K.Hunt","preferred_name":"Kareem","birth_date":"1995-08-06","weight":216.0,"height":71,"position":"RB","birth_place":"Willoughby, OH, USA","high_school":"South (OH)","college":"Toledo","college_conf":"Mid-American Conference","rookie_year":2017,"status":"A01","sr_id":"sr:player:1129873","draft":{"year":2017,"round":3,"number":86,"team":{"id":"6680d28d-d4d2-49f6-aace-5292d3ec02c2","name":"Chiefs","market":"Kansas City","alias":"KC","sr_id":"sr:competitor:4422"}},"references":[{"id":"00-0033923","origin":"gsis"},{"id":"44898","origin":"nflx"}]},{"id":"1283923a-9716-4936-920a-a57f019bb2e8","name":"Marvin Hall","jersey":"18","last_name":"Hall","first_name":"Marvin","abbr_name":"M.Hall","preferred_name":"Marvin","birth_date":"1993-04-10","weight":190.0,"height":70,"position":"WR","birth_place":"Los Angeles, CA, USA","high_school":"Dorsey (CA)","college":"Washington","college_conf":"Pacific Twelve Conference","rookie_year":2016,"status":"A01","sr_id":"sr:player:1086148","references":[{"id":"00-0033094","origin":"gsis"},{"id":"44074","origin":"nflx"}]},{"id":"12f4a38f-17b4-42b1-a1e6-9fd6ef08d150","name":"Kevin Johnson","jersey":"28","last_name":"Johnson","first_name":"Kevin","abbr_name":"K.Johnson","preferred_name":"Kevin","birth_date":"1992-08-05","weight":185.0,"height":72,"position":"CB","birth_place":"Clarksville, MD, USA","high_school":"River Hill (MD)","college":"Wake Forest","college_conf":"Atlantic Coast Conference","rookie_year":2015,"status":"A01","sr_id":"sr:player:834531","draft":{"year":2015,"round":1,"number":16,"team":{"id":"82d2d380-3834-4938-835f-aec541e5ece7","name":"Texans","market":"Houston","alias":"HOU","sr_id":"sr:competitor:4324"}},"references":[{"id":"00-0031548","origin":"gsis"},{"id":"42359","origin":"nflx"}]},{"id":"1b3d350a-478b-4542-a430-d12cc96adc22","name":"Case Keenum","jersey":"5","last_name":"Keenum","first_name":"Case","abbr_name":"C.Keenum","preferred_name":"Case","birth_date":"1988-02-17","weight":215.0,"height":73,"position":"QB","birth_place":"Brownwood, TX, USA","high_school":"Wylie (TX)","college":"Houston","college_conf":"American Athletic Conference","rookie_year":2012,"status":"A01","sr_id":"sr:player:829063","references":[{"id":"00-0028986","origin":"gsis"},{"id":"38937","origin":"nflx"}]},{"id":"1bbe7ce0-3707-4d4d-b8f6-7577008f1763","name":"Grant Delpit","jersey":"22","last_name":"Delpit","first_name":"Grant","abbr_name":"G.Delpit","preferred_name":"Grant","birth_date":"1998-09-20","weight":203.0,"height":75,"position":"FS","birth_place":"Houston, TX, USA","high_school":"IMG Academy (FL)","college":"Louisiana State","college_conf":"Southeastern Conference","rookie_year":2020,"status":"A01","sr_id":"sr:player:2039999","draft":{"year":2020,"round":2,"number":44,"team":{"id":"d5a2eb42-8065-4174-ab79-0a6fa820e35e","name":"Browns","market":"Cleveland","alias":"CLE","sr_id":"sr:competitor:4417"}},"references":[{"id":"52452","origin":"nflx"},{"id":"00-0036282","origin":"gsis"}]},{"id":"20395574-a767-44be-8e79-e1b15eef0f11","name":"Porter Gustin","jersey":"97","last_name":"Gustin","first_name":"Porter","abbr_name":"P.Gustin","preferred_name":"Porter","birth_date":"1997-02-08","weight":260.0,"height":77,"position":"DE","birth_place":"Elk Ridge, UT, USA","high_school":"Salem Hills (UT)","college":"Southern California","college_conf":"Pacific Twelve Conference","rookie_year":2019,"status":"A01","sr_id":"sr:player:1742561","references":[{"id":"48539","origin":"nflx"},{"id":"00-0035404","origin":"gsis"}]},{"id":"27156b0b-e82d-4d02-8a04-ca1891d77110","name":"John Kelly","jersey":"42","last_name":"Kelly","first_name":"John","abbr_name":"J.Kelly","preferred_name":"John","birth_date":"1996-10-04","weight":205.0,"height":70,"position":"RB","birth_place":"Detroit, MI, USA","high_school":"Oak Park (MI)","college":"Tennessee","college_conf":"Southeastern Conference","rookie_year":2018,"status":"A01","sr_id":"sr:player:1217942","draft":{"year":2018,"round":6,"number":176,"team":{"id":"2eff2a03-54d4-46ba-890e-2bc3925548f3","name":"Rams","market":"Los Angeles","alias":"LA","sr_id":"sr:competitor:4387"}},"references":[{"id":"46245","origin":"nflx"},{"id":"00-0034808","origin":"gsis"}]},{"id":"29972cbe-2912-49df-916b-200eead9a218","name":"Taywan Taylor","jersey":"10","last_name":"Taylor","first_name":"Taywan","abbr_name":"T.Taylor","preferred_name":"Taywan","birth_date":"1995-03-02","weight":203.0,"height":71,"position":"WR","birth_place":"Louisville, KY, USA","high_school":"Pleasure Ridge Park (KY)","college":"Western Kentucky","college_conf":"Conference USA","rookie_year":2017,"status":"A01","sr_id":"sr:player:1129727","draft":{"year":2017,"round":3,"number":72,"team":{"id":"d26a1ca5-722d-4274-8f97-c92e49c96315","name":"Titans","market":"Tennessee","alias":"TEN","sr_id":"sr:competitor:367364"}},"references":[{"id":"44884","origin":"nflx"},{"id":"00-0033911","origin":"gsis"}]},{"id":"2b6a749f-5e78-484f-8a87-92c6da991b19","name":"Wyatt Teller","jersey":"77","last_name":"Teller","first_name":"Wyatt","abbr_name":"W.Teller","preferred_name":"Wyatt","birth_date":"1994-11-21","weight":315.0,"height":76,"position":"G","birth_place":"Manassas, VA, USA","high_school":"Liberty (VA)","college":"Virginia Tech","college_conf":"Atlantic Coast Conference","rookie_year":2018,"status":"A01","sr_id":"sr:player:1475050","draft":{"year":2018,"round":5,"number":166,"team":{"id":"768c92aa-75ff-4a43-bcc0-f2798c2e1724","name":"Bills","market":"Buffalo","alias":"BUF","sr_id":"sr:competitor:4376"}},"references":[{"id":"46235","origin":"nflx"},{"id":"00-0034399","origin":"gsis"}]},{"id":"2c35ed5f-7317-4776-8ee7-0438e0286508","name":"Andy Janovich","jersey":"31","last_name":"Janovich","first_name":"Andy","abbr_name":"A.Janovich","preferred_name":"Andy","birth_date":"1993-05-23","weight":238.0,"height":73,"position":"FB","birth_place":"Omaha, NE, USA","high_school":"Gretna (NE)","college":"Nebraska","college_conf":"Big Ten Conference","rookie_year":2016,"status":"A01","sr_id":"sr:player:988745","draft":{"year":2016,"round":6,"number":176,"team":{"id":"ce92bd47-93d5-4fe9-ada4-0fc681e6caa0","name":"Broncos","market":"Denver","alias":"DEN","sr_id":"sr:competitor:4418"}},"references":[{"id":"00-0032956","origin":"gsis"},{"id":"43465","origin":"nflx"}]},{"id":"2d52ede5-1c65-4f18-a8ac-9306192ef625","name":"JoJo Natson","jersey":"19","last_name":"Natson","first_name":"JoJo","abbr_name":"J.Natson","preferred_name":"JoJo","birth_date":"1994-02-01","weight":153.0,"height":67,"position":"WR","birth_place":"Fort Lauderdale, FL, USA","high_school":"Boyd Anderson (FL)","college":"Akron","college_conf":"Mid-American Conference","rookie_year":2017,"status":"A01","sr_id":"sr:player:1523099","references":[{"id":"00-0033266","origin":"gsis"},{"id":"45150","origin":"nflx"}]},{"id":"30198d30-9769-4e10-ac86-b4c91d940802","name":"Baker Mayfield","jersey":"6","last_name":"Mayfield","first_name":"Baker","abbr_name":"B.Mayfield","preferred_name":"Baker","birth_date":"1995-04-14","weight":215.0,"height":73,"position":"QB","birth_place":"Austin, TX, USA","high_school":"Lake Travis (TX)","college":"Oklahoma","college_conf":"Big Twelve Conference","rookie_year":2018,"status":"A01","sr_id":"sr:player:1217750","draft":{"year":2018,"round":1,"number":1,"team":{"id":"d5a2eb42-8065-4174-ab79-0a6fa820e35e","name":"Browns","market":"Cleveland","alias":"CLE","sr_id":"sr:competitor:4417"}},"references":[{"id":"46070","origin":"nflx"},{"id":"00-0034855","origin":"gsis"}]},{"id":"32b601e7-4491-479a-895a-2f96add83e09","name":"Sheldrick Redwine","jersey":"29","last_name":"Redwine","first_name":"Sheldrick","abbr_name":"S.Redwine","preferred_name":"Sheldrick","birth_date":"1996-11-06","weight":196.0,"height":72,"position":"FS","birth_place":"Miami, FL, USA","high_school":"Miami Killian (FL)","college":"Miami","college_conf":"Atlantic Coast Conference","rookie_year":2019,"status":"A01","sr_id":"sr:player:1216786","draft":{"year":2019,"round":4,"number":119,"team":{"id":"d5a2eb42-8065-4174-ab79-0a6fa820e35e","name":"Browns","market":"Cleveland","alias":"CLE","sr_id":"sr:competitor:4417"}},"references":[{"id":"00-0034977","origin":"gsis"},{"id":"47902","origin":"nflx"}]},{"id":"354dec38-b88b-4ba0-8974-859123f27c45","name":"Odell Beckham Jr.","jersey":"13","last_name":"Beckham","first_name":"Odell","abbr_name":"O.Beckham Jr.","preferred_name":"Odell","birth_date":"1992-11-05","weight":198.0,"height":71,"position":"WR","birth_place":"New Orleans, LA, USA","high_school":"Isidore Newman (LA)","college":"Louisiana State","college_conf":"Southeastern Conference","rookie_year":2014,"status":"A01","sr_id":"sr:player:828649","name_suffix":"Jr.","draft":{"year":2014,"round":1,"number":12,"team":{"id":"04aa1c9d-66da-489d-b16a-1dee3f2eec4d","name":"Giants","market":"New York","alias":"NYG","sr_id":"sr:competitor:4426"}},"references":[{"id":"41238","origin":"nflx"},{"id":"00-0031235","origin":"gsis"}]},{"id":"36b878c8-7d53-4e90-8403-6f67fa911a2e","name":"Trevon Young","jersey":"59","last_name":"Young","first_name":"Trevon","abbr_name":"T.Young","preferred_name":"Trevon","birth_date":"1995-04-01","weight":259.0,"height":76,"position":"OLB","birth_place":"Des Moines, IA, USA","high_school":"Lincoln (IA)","college":"Louisville","college_conf":"Atlantic Coast Conference","rookie_year":2018,"status":"A01","sr_id":"sr:player:1474758","draft":{"year":2018,"round":6,"number":205,"team":{"id":"2eff2a03-54d4-46ba-890e-2bc3925548f3","name":"Rams","market":"Los Angeles","alias":"LA","sr_id":"sr:competitor:4387"}},"references":[{"id":"46274","origin":"nflx"},{"id":"00-0034811","origin":"gsis"}]},{"id":"39ee3bee-1177-49cd-a78b-7a790ffd0b84","name":"Andrew Sendejo","jersey":"23","last_name":"Sendejo","first_name":"Andrew","abbr_name":"A.Sendejo","preferred_name":"Andrew","birth_date":"1987-09-09","weight":210.0,"height":73,"position":"FS","birth_place":"San Antonio, TX, USA","high_school":"Smithson Valley (TX)","college":"Rice","college_conf":"Conference USA","rookie_year":2010,"status":"A01","sr_id":"sr:player:828713","references":[{"id":"36712","origin":"nflx"},{"id":"00-0027914","origin":"gsis"}]},{"id":"3a337668-7978-4310-b17c-8e1279ba4a4d","name":"Kyle Markway","jersey":"86","last_name":"Markway","first_name":"Kyle","abbr_name":"K.Markway","preferred_name":"Kyle","birth_date":"1997-03-04","weight":250.0,"height":76,"position":"TE","birth_place":"St. Louis, MO, USA","high_school":"St. John Vianney (MO)","college":"South Carolina","college_conf":"Southeastern Conference","rookie_year":2020,"status":"A01","sr_id":"sr:player:2040437","references":[{"id":"00-0035817","origin":"gsis"},{"id":"52719","origin":"nflx"}]},{"id":"3be41614-5c70-4b0a-89c7-c7ae061d9223","name":"Olivier Vernon","jersey":"54","last_name":"Vernon","first_name":"Olivier","abbr_name":"O.Vernon","preferred_name":"Olivier","birth_date":"1990-10-07","weight":262.0,"height":74,"position":"DE","birth_place":"Miami, FL, USA","high_school":"American (FL)","college":"Miami","college_conf":"Atlantic Coast Conference","rookie_year":2012,"status":"A01","sr_id":"sr:player:831231","draft":{"year":2012,"round":3,"number":72,"team":{"id":"4809ecb0-abd3-451d-9c4a-92a90b83ca06","name":"Dolphins","market":"Miami","alias":"MIA","sr_id":"sr:competitor:4287"}},"references":[{"id":"38602","origin":"nflx"},{"id":"00-0029693","origin":"gsis"}]},{"id":"3d405d21-bfdd-4495-afe3-9e96d1972ee2","name":"M.J. Stewart","jersey":"36","last_name":"Stewart","first_name":"M.J.","abbr_name":"M.Stewart","preferred_name":"M.J.","birth_date":"1995-09-16","weight":205.0,"height":71,"position":"CB","birth_place":"Arlington, VA, USA","high_school":"Yorktown (VA)","college":"North Carolina","college_conf":"Atlantic Coast Conference","rookie_year":2018,"status":"A01","sr_id":"sr:player:1474040","draft":{"year":2018,"round":2,"number":53,"team":{"id":"4254d319-1bc7-4f81-b4ab-b5e6f3402b69","name":"Buccaneers","market":"Tampa Bay","alias":"TB","sr_id":"sr:competitor:4388"}},"references":[{"id":"46122","origin":"nflx"},{"id":"00-0034355","origin":"gsis"}]},{"id":"43a74ae6-ddb7-405e-8ccd-69d14da6c374","name":"Charley Hughlett","jersey":"47","last_name":"Hughlett","first_name":"Charley","abbr_name":"C.Hughlett","preferred_name":"Charley","birth_date":"1990-05-16","weight":248.0,"height":76,"position":"LS","birth_place":"Tampa, FL, USA","high_school":"Hillsborough (FL)","college":"Central Florida","college_conf":"Conference USA","rookie_year":2012,"status":"A01","sr_id":"sr:player:831147","references":[{"id":"00-0029008","origin":"gsis"},{"id":"38955","origin":"nflx"}]},{"id":"445efcfc-1646-4823-89f7-8b6005266d13","name":"Jordan Elliott","jersey":"90","last_name":"Elliott","first_name":"Jordan","abbr_name":"J.Elliott","preferred_name":"Jordan","birth_date":"1997-11-23","weight":315.0,"height":76,"position":"DT","birth_place":"Missouri City, TX, USA","high_school":"Westside (TX)","college":"Missouri","college_conf":"Southeastern Conference","rookie_year":2020,"status":"A01","sr_id":"sr:player:2040387","draft":{"year":2020,"round":3,"number":88,"team":{"id":"d5a2eb42-8065-4174-ab79-0a6fa820e35e","name":"Browns","market":"Cleveland","alias":"CLE","sr_id":"sr:competitor:4417"}},"references":[{"id":"00-0036266","origin":"gsis"},{"id":"52496","origin":"nflx"}]},{"id":"471db686-fa8e-484c-8525-0169b0a8f773","name":"Sione Takitaki","jersey":"44","last_name":"Takitaki","first_name":"Sione","abbr_name":"S.Takitaki","preferred_name":"Sione","birth_date":"1995-06-08","weight":238.0,"height":73,"position":"OLB","birth_place":"Fontana, CA, USA","high_school":"Heritage (CA)","college":"Brigham Young","college_conf":"Independent","rookie_year":2019,"status":"A01","sr_id":"sr:player:1188552","draft":{"year":2019,"round":3,"number":80,"team":{"id":"d5a2eb42-8065-4174-ab79-0a6fa820e35e","name":"Browns","market":"Cleveland","alias":"CLE","sr_id":"sr:competitor:4417"}},"references":[{"id":"00-0035646","origin":"gsis"},{"id":"47863","origin":"nflx"}]},{"id":"491a4774-9f2d-4b70-9933-2c7c89abbeba","name":"Alex Taylor","jersey":"60","last_name":"Taylor","first_name":"Alex","abbr_name":"A.Taylor","preferred_name":"Alex","birth_date":"1997-04-29","weight":294.0,"height":81,"position":"T","birth_place":"Moncks Corner, SC, USA","high_school":"Berkeley (SC)","college":"South Carolina State","college_conf":"Mid-Eastern Athletic Conference","rookie_year":2020,"status":"A01","sr_id":"sr:player:1218180","references":[{"id":"00-0036120","origin":"gsis"},{"id":"53024","origin":"nflx"}]},{"id":"4a7d7bfc-9fe6-4869-a741-d5d17b177edc","name":"Elijah Benton","jersey":"48","last_name":"Benton","first_name":"Elijah","abbr_name":"E.Benton","preferred_name":"Elijah","birth_date":"1996-09-05","weight":205.0,"height":73,"position":"SS","birth_place":"Forest, VA, USA","high_school":"Liberty Christian Academy (VA)","college":"Liberty","college_conf":"Independent","rookie_year":2020,"status":"A01","sr_id":"sr:player:1184114","references":[{"id":"00-0036109","origin":"gsis"},{"id":"53013","origin":"nflx"}]},{"id":"4b99ead5-0f79-4899-84a7-075c08890698","name":"Cody Parkey","jersey":"2","last_name":"Parkey","first_name":"Cody","abbr_name":"C.Parkey","preferred_name":"Cody","birth_date":"1992-02-19","weight":190.0,"height":72,"position":"K","birth_place":"Jupiter, FL, USA","high_school":"Jupiter (FL)","college":"Auburn","college_conf":"Southeastern Conference","rookie_year":2014,"status":"A01","sr_id":"sr:player:855630","references":[{"id":"41688","origin":"nflx"},{"id":"00-0030850","origin":"gsis"}]},{"id":"4bd60b33-9fbf-4156-ba2b-8264ac37b418","name":"Nick Chubb","jersey":"24","last_name":"Chubb","first_name":"Nick","abbr_name":"N.Chubb","preferred_name":"Nick","birth_date":"1995-12-27","weight":225.0,"height":71,"position":"RB","birth_place":"Cedartown, GA, USA","high_school":"Cedartown (GA)","college":"Georgia","college_conf":"Southeastern Conference","rookie_year":2018,"status":"A01","sr_id":"sr:player:1235684","draft":{"year":2018,"round":2,"number":35,"team":{"id":"d5a2eb42-8065-4174-ab79-0a6fa820e35e","name":"Browns","market":"Cleveland","alias":"CLE","sr_id":"sr:competitor:4417"}},"references":[{"id":"46104","origin":"nflx"},{"id":"00-0034791","origin":"gsis"}]},{"id":"501aa2d9-4202-40e8-810b-92cacea26cd7","name":"Jordan Franks","jersey":"88","last_name":"Franks","first_name":"Jordan","abbr_name":"J.Franks","preferred_name":"Jordan","birth_date":"1996-02-01","weight":239.0,"height":76,"position":"TE","birth_place":"Tallahassee, FL, USA","high_school":"Wakulla (FL)","college":"Central Florida","college_conf":"American Athletic Conference","rookie_year":2018,"status":"A01","sr_id":"sr:player:1183768","references":[{"id":"00-0034532","origin":"gsis"},{"id":"46716","origin":"nflx"}]},{"id":"543deccb-0e8d-42ac-b213-dfd458fc0602","name":"Jedrick Wills","jersey":"71","last_name":"Wills","first_name":"Jedrick","abbr_name":"J.Wills","preferred_name":"Jedrick","birth_date":"1999-05-17","weight":320.0,"height":77,"position":"T","birth_place":"Lexington, KY, USA","high_school":"Lafayette (KY)","college":"Alabama","college_conf":"Southeastern Conference","rookie_year":2020,"status":"A01","sr_id":"sr:player:2040399","draft":{"year":2020,"round":1,"number":10,"team":{"id":"d5a2eb42-8065-4174-ab79-0a6fa820e35e","name":"Browns","market":"Cleveland","alias":"CLE","sr_id":"sr:competitor:4417"}},"references":[{"id":"00-0036267","origin":"gsis"},{"id":"52418","origin":"nflx"}]},{"id":"54feeb01-a1d6-4313-b8b5-5663f698b5bd","name":"Greedy Williams","jersey":"26","last_name":"Williams","first_name":"Greedy","abbr_name":"G.Williams","preferred_name":"Greedy","birth_date":"1997-12-03","weight":184.0,"height":74,"position":"CB","birth_place":"Shreveport, LA, USA","high_school":"Calvary Baptist Academy (LA)","college":"Louisiana State","college_conf":"Southeastern Conference","rookie_year":2019,"status":"A01","sr_id":"sr:player:1734751","draft":{"year":2019,"round":2,"number":46,"team":{"id":"d5a2eb42-8065-4174-ab79-0a6fa820e35e","name":"Browns","market":"Cleveland","alias":"CLE","sr_id":"sr:competitor:4417"}},"references":[{"id":"00-0035638","origin":"gsis"},{"id":"47829","origin":"nflx"}]},{"id":"5f313f6e-4a5b-495b-8442-176c145f68c4","name":"Curtis Weaver","jersey":"61","last_name":"Weaver","first_name":"Curtis","abbr_name":"C.Weaver","preferred_name":"Curtis","birth_date":"1998-08-03","weight":265.0,"height":75,"position":"DE","birth_place":"Long Beach, CA, USA","high_school":"St. Anthony (CA)","college":"Boise State","college_conf":"Mountain West Conference","rookie_year":2020,"status":"A01","sr_id":"sr:player:2040227","draft":{"year":2020,"round":5,"number":164,"team":{"id":"4809ecb0-abd3-451d-9c4a-92a90b83ca06","name":"Dolphins","market":"Miami","alias":"MIA","sr_id":"sr:competitor:4287"}},"references":[{"id":"00-0036216","origin":"gsis"},{"id":"52572","origin":"nflx"}]},{"id":"6259f62d-e16f-4369-a3be-ca02f79f3026","name":"Ryan Switzer","jersey":"10","last_name":"Switzer","first_name":"Ryan","abbr_name":"R.Switzer","preferred_name":"Ryan","birth_date":"1994-11-04","weight":185.0,"height":68,"position":"WR","birth_place":"Charleston, WV, USA","high_school":"George Washington (WV)","college":"North Carolina","college_conf":"Atlantic Coast Conference","rookie_year":2017,"status":"A01","sr_id":"sr:player:1130155","draft":{"year":2017,"round":4,"number":133,"team":{"id":"e627eec7-bbae-4fa4-8e73-8e1d6bc5c060","name":"Cowboys","market":"Dallas","alias":"DAL","sr_id":"sr:competitor:4392"}},"references":[{"id":"00-0033562","origin":"gsis"},{"id":"44946","origin":"nflx"}]},{"id":"671d2fd7-41bb-457a-8e93-904ee7d94eb1","name":"J.C. Tretter","jersey":"64","last_name":"Tretter","first_name":"J.C.","abbr_name":"J.Tretter","preferred_name":"J.C.","birth_date":"1991-02-12","weight":307.0,"height":76,"position":"C","birth_place":"Akron, NY, USA","high_school":"Akron Central (NY)","college":"Cornell","college_conf":"Ivy League","rookie_year":2013,"status":"A01","sr_id":"sr:player:827603","draft":{"year":2013,"round":4,"number":122,"team":{"id":"a20471b4-a8d9-40c7-95ad-90cc30e46932","name":"Packers","market":"Green Bay","alias":"GB","sr_id":"sr:competitor:4420"}},"references":[{"id":"00-0030076","origin":"gsis"},{"id":"40070","origin":"nflx"}]},{"id":"67760ee1-c969-488f-b449-b8c37e7e32bb","name":"Andrew Billings","jersey":"99","last_name":"Billings","first_name":"Andrew","abbr_name":"A.Billings","preferred_name":"Andrew","birth_date":"1995-03-06","weight":328.0,"height":73,"position":"NT","birth_place":"Waco, TX, USA","high_school":"Waco (TX)","college":"Baylor","college_conf":"Big Twelve Conference","rookie_year":2016,"status":"R62","sr_id":"sr:player:988647","draft":{"year":2016,"round":4,"number":122,"team":{"id":"ad4ae08f-d808-42d5-a1e6-e9bc4e34d123","name":"Bengals","market":"Cincinnati","alias":"CIN","sr_id":"sr:competitor:4416"}},"references":[{"id":"43411","origin":"nflx"},{"id":"00-0033066","origin":"gsis"}]},{"id":"6f124753-5c6c-454b-97c7-0f9b4d14e7c2","name":"KhaDarel Hodge","jersey":"12","last_name":"Hodge","first_name":"Khadarel","abbr_name":"K.Hodge","preferred_name":"Khadarel","birth_date":"1995-01-03","weight":205.0,"height":74,"position":"WR","birth_place":"D'Lo, MS, USA","high_school":"Mendenhall (MS)","college":"Prairie View","college_conf":"Southwestern Athletic Conference","rookie_year":2018,"status":"A01","sr_id":"sr:player:1548717","references":[{"id":"46992","origin":"nflx"},{"id":"00-0034854","origin":"gsis"}]},{"id":"741c1ab2-378b-45ce-86c7-533e6a031f22","name":"Karl Joseph","jersey":"42","last_name":"Joseph","first_name":"Karl","abbr_name":"K.Joseph","preferred_name":"Karl","birth_date":"1993-09-08","weight":200.0,"height":70,"position":"SS","birth_place":"Orlando, FL, USA","high_school":"Edgewater (FL)","college":"West Virginia","college_conf":"Big Twelve Conference","rookie_year":2016,"status":"A01","sr_id":"sr:player:986897","draft":{"year":2016,"round":1,"number":14,"team":{"id":"7d4fcc64-9cb5-4d1b-8e75-8a906d1e1576","name":"Raiders","market":"Las Vegas","alias":"LV","sr_id":"sr:competitor:4390"}},"references":[{"id":"00-0032888","origin":"gsis"},{"id":"43303","origin":"nflx"}]},{"id":"7475baa8-7662-49be-9b41-526450f28bfc","name":"Javon Patterson","jersey":"63","last_name":"Patterson","first_name":"Javon","abbr_name":"J.Patterson","preferred_name":"Javon","birth_date":"1997-07-08","weight":307.0,"height":75,"position":"C","birth_place":"Petal, MS, USA","high_school":"Petal (MS)","college":"Mississippi","college_conf":"Southeastern Conference","rookie_year":2019,"status":"A01","sr_id":"sr:player:1228164","draft":{"year":2019,"round":7,"number":246,"team":{"id":"82cf9565-6eb9-4f01-bdbd-5aa0d472fcd9","name":"Colts","market":"Indianapolis","alias":"IND","sr_id":"sr:competitor:4421"}},"references":[{"id":"48029","origin":"nflx"},{"id":"00-0035005","origin":"gsis"}]},{"id":"7ca273b2-a4bc-44c4-a670-98d86942adb5","name":"Montrel Meander","jersey":"41","last_name":"Meander","first_name":"Montrel","abbr_name":"M.Meander","preferred_name":"Montrel","birth_date":"1994-09-20","weight":215.0,"height":74,"position":"SS","birth_place":"Amarillo, TX, USA","high_school":"Palo Duro (TX)","college":"Grambling","college_conf":"Southwestern Athletic Conference","rookie_year":2018,"status":"A01","sr_id":"sr:player:1475924","references":[{"id":"00-0034255","origin":"gsis"},{"id":"46508","origin":"nflx"}]},{"id":"7e34053d-00bf-4f3f-a464-329c8f5057d0","name":"Rashard Higgins","jersey":"82","last_name":"Higgins","first_name":"Rashard","abbr_name":"R.Higgins","preferred_name":"Rashard","birth_date":"1994-10-07","weight":198.0,"height":73,"position":"WR","birth_place":"Dallas, TX, USA","high_school":"Mesquite (TX)","college":"Colorado State","college_conf":"Mountain West Conference","rookie_year":2016,"status":"A01","sr_id":"sr:player:988711","draft":{"year":2016,"round":5,"number":172,"team":{"id":"d5a2eb42-8065-4174-ab79-0a6fa820e35e","name":"Browns","market":"Cleveland","alias":"CLE","sr_id":"sr:competitor:4417"}},"references":[{"id":"00-0032977","origin":"gsis"},{"id":"43461","origin":"nflx"}]},{"id":"81e211e1-547a-4475-bcf6-8c8ffde057f5","name":"Sheldon Richardson","jersey":"98","last_name":"Richardson","first_name":"Sheldon","abbr_name":"S.Richardson","preferred_name":"Sheldon","birth_date":"1990-11-29","weight":294.0,"height":75,"position":"DT","birth_place":"St. Louis, MO, USA","high_school":"Gateway Tech (MO)","college":"Missouri","college_conf":"Southeastern Conference","rookie_year":2013,"status":"A01","sr_id":"sr:player:828945","draft":{"year":2013,"round":1,"number":13,"team":{"id":"5fee86ae-74ab-4bdd-8416-42a9dd9964f3","name":"Jets","market":"New York","alias":"NYJ","sr_id":"sr:competitor:4427"}},"references":[{"id":"00-0030573","origin":"gsis"},{"id":"39959","origin":"nflx"}]},{"id":"85e3651c-cde0-48ed-a5ea-93477a1fe99b","name":"Johnny Stanton","jersey":"43","last_name":"Stanton","first_name":"Johnny","abbr_name":"J.Stanton","preferred_name":"Johnny","birth_date":"1994-09-07","weight":245.0,"height":74,"position":"FB","birth_place":"Ranch Santa Margarita, CA, USA","high_school":"Santa Margarita Catholic (CA)","college":"Nevada-Las Vegas","college_conf":"Mountain West Conference","rookie_year":2018,"status":"A01","sr_id":"sr:player:1190502","references":[{"id":"46536","origin":"nflx"},{"id":"00-0034311","origin":"gsis"}]},{"id":"894c783a-ddcd-4dba-b337-06d7db037a6e","name":"Jacob Phillips","jersey":"50","last_name":"Phillips","first_name":"Jacob","abbr_name":"J.Phillips","preferred_name":"Jacob","birth_date":"1999-04-01","weight":233.0,"height":76,"position":"OLB","birth_place":"Nashville, TN, USA","high_school":"East Nashville (TN)","college":"Louisiana State","college_conf":"Southeastern Conference","rookie_year":2020,"status":"A01","sr_id":"sr:player:2040215","draft":{"year":2020,"round":3,"number":97,"team":{"id":"d5a2eb42-8065-4174-ab79-0a6fa820e35e","name":"Browns","market":"Cleveland","alias":"CLE","sr_id":"sr:competitor:4417"}},"references":[{"id":"00-0036276","origin":"gsis"},{"id":"52505","origin":"nflx"}]},{"id":"8b44e3b8-81ae-4f02-b598-965872d12816","name":"Cameron Malveaux","jersey":"69","last_name":"Malveaux","first_name":"Cameron","abbr_name":"C.Malveaux","preferred_name":"Cameron","birth_date":"1994-09-22","weight":265.0,"height":77,"position":"DE","birth_place":"Beaumont, TX, USA","high_school":"Hamshire-Fannett (TX)","college":"Houston","college_conf":"American Athletic Conference","rookie_year":2017,"status":"A01","sr_id":"sr:player:1133761","references":[{"id":"45300","origin":"nflx"},{"id":"00-0033403","origin":"gsis"}]},{"id":"8f0e2ff1-fa77-4049-aa94-159a37ed5c51","name":"Drew Forbes","jersey":"79","last_name":"Forbes","first_name":"Drew","abbr_name":"D.Forbes","preferred_name":"Drew","birth_date":"1997-01-18","weight":305.0,"height":77,"position":"T","birth_place":"Bonne Terre, MO, USA","high_school":"North County (MO)","college":"Southeast Missouri","college_conf":"Ohio Valley Conference","rookie_year":2019,"status":"R62","sr_id":"sr:player:1189054","draft":{"year":2019,"round":6,"number":189,"team":{"id":"d5a2eb42-8065-4174-ab79-0a6fa820e35e","name":"Browns","market":"Cleveland","alias":"CLE","sr_id":"sr:competitor:4417"}},"references":[{"id":"00-0034991","origin":"gsis"},{"id":"47972","origin":"nflx"}]},{"id":"8f86fcea-90e8-49ea-bc78-5c7659313e57","name":"David Njoku","jersey":"85","last_name":"Njoku","first_name":"David","abbr_name":"D.Njoku","preferred_name":"David","birth_date":"1996-07-10","weight":246.0,"height":76,"position":"TE","birth_place":"Cedar Grove, NJ, USA","high_school":"Cedar Grove (NJ)","college":"Miami","college_conf":"Atlantic Coast Conference","rookie_year":2017,"status":"A01","sr_id":"sr:player:1129533","draft":{"year":2017,"round":1,"number":29,"team":{"id":"d5a2eb42-8065-4174-ab79-0a6fa820e35e","name":"Browns","market":"Cleveland","alias":"CLE","sr_id":"sr:competitor:4417"}},"references":[{"id":"44841","origin":"nflx"},{"id":"00-0033885","origin":"gsis"}]},{"id":"90c2a93f-d837-4e1b-b57c-56648903a8db","name":"Austin Hooper","jersey":"81","last_name":"Hooper","first_name":"Austin","abbr_name":"A.Hooper","preferred_name":"Austin","birth_date":"1994-10-29","weight":254.0,"height":76,"position":"TE","birth_place":"San Mateo, CA, USA","high_school":"De La Salle (CA)","college":"Stanford","college_conf":"Pacific Twelve Conference","rookie_year":2016,"status":"A01","sr_id":"sr:player:1073962","draft":{"year":2016,"round":3,"number":81,"team":{"id":"e6aa13a4-0055-48a9-bc41-be28dc106929","name":"Falcons","market":"Atlanta","alias":"ATL","sr_id":"sr:competitor:4393"}},"references":[{"id":"43370","origin":"nflx"},{"id":"00-0032392","origin":"gsis"}]},{"id":"915f567f-ca74-426a-8ed0-123c45f67baa","name":"Larry Ogunjobi","jersey":"65","last_name":"Ogunjobi","first_name":"Larry","abbr_name":"L.Ogunjobi","preferred_name":"Larry","birth_date":"1994-06-03","weight":305.0,"height":75,"position":"DT","birth_place":"Greensboro, NC, USA","high_school":"Ragsdale (NC)","college":"North Carolina-Charlotte","college_conf":"Conference USA","rookie_year":2017,"status":"A01","sr_id":"sr:player:1129801","draft":{"year":2017,"round":3,"number":65,"team":{"id":"d5a2eb42-8065-4174-ab79-0a6fa820e35e","name":"Browns","market":"Cleveland","alias":"CLE","sr_id":"sr:competitor:4417"}},"references":[{"id":"44877","origin":"nflx"},{"id":"00-0033905","origin":"gsis"}]},{"id":"924edb03-29a9-42ae-92dd-ef7e8a498095","name":"Donovan Peoples-Jones","jersey":"11","last_name":"Peoples-Jones","first_name":"Donovan","abbr_name":"D.Peoples-Jones","preferred_name":"Donovan","birth_date":"1999-02-19","weight":208.0,"height":74,"position":"WR","birth_place":"Detroit, MI, USA","high_school":"Cass Tech (MI)","college":"Michigan","college_conf":"Big Ten Conference","rookie_year":2020,"status":"A01","sr_id":"sr:player:2040213","draft":{"year":2020,"round":6,"number":187,"team":{"id":"d5a2eb42-8065-4174-ab79-0a6fa820e35e","name":"Browns","market":"Cleveland","alias":"CLE","sr_id":"sr:competitor:4417"}},"references":[{"id":"52595","origin":"nflx"},{"id":"00-0036233","origin":"gsis"}]},{"id":"94f04ef5-238a-4f38-b45a-de2e7f3b9f9e","name":"Terrance Mitchell","jersey":"39","last_name":"Mitchell","first_name":"Terrance","abbr_name":"T.Mitchell","preferred_name":"Terrance","birth_date":"1992-05-17","weight":190.0,"height":71,"position":"CB","birth_place":"Sacramento, CA, USA","high_school":"Luther Burbank (CA)","college":"Oregon","college_conf":"Pacific Twelve Conference","rookie_year":2014,"status":"A01","sr_id":"sr:player:852658","draft":{"year":2014,"round":7,"number":254,"team":{"id":"e627eec7-bbae-4fa4-8e73-8e1d6bc5c060","name":"Cowboys","market":"Dallas","alias":"DAL","sr_id":"sr:competitor:4392"}},"references":[{"id":"41483","origin":"nflx"},{"id":"00-0031097","origin":"gsis"}]},{"id":"955c65c6-5557-4525-a549-3fab45765cec","name":"Cordel Iwuagwu","jersey":"67","last_name":"Iwuagwu","first_name":"Cordel","abbr_name":"C.Iwuagwu","preferred_name":"Cordel","birth_date":"1996-09-04","weight":311.0,"height":75,"position":"G","birth_place":"Houston, TX, USA","high_school":"Westfield (TX)","college":"Texas Christian","college_conf":"Big Twelve Conference","rookie_year":2020,"status":"A01","sr_id":"sr:player:2065133","references":[{"id":"52969","origin":"nflx"},{"id":"00-0036066","origin":"gsis"}]},{"id":"981cfb99-ff6f-452e-806c-116f56a484a5","name":"B.J. Goodson","jersey":"93","last_name":"Goodson","first_name":"B.J.","abbr_name":"B.Goodson","preferred_name":"B.J.","birth_date":"1993-05-29","weight":242.0,"height":73,"position":"ILB","birth_place":"Lamar, SC, USA","high_school":"Lamar (SC)","college":"Clemson","college_conf":"Atlantic Coast Conference","rookie_year":2016,"status":"A01","sr_id":"sr:player:988659","draft":{"year":2016,"round":4,"number":109,"team":{"id":"04aa1c9d-66da-489d-b16a-1dee3f2eec4d","name":"Giants","market":"New York","alias":"NYG","sr_id":"sr:competitor:4426"}},"references":[{"id":"00-0033121","origin":"gsis"},{"id":"43398","origin":"nflx"}]},{"id":"9b96ef63-04bd-41ae-b59c-acc0f2561d19","name":"Ronnie Harrison","jersey":"33","last_name":"Harrison","first_name":"Ronnie","abbr_name":"R.Harrison","preferred_name":"Ronnie","birth_date":"1997-04-18","weight":214.0,"height":75,"position":"SS","birth_place":"Tallahassee, FL, USA","high_school":"Florida State University School (FL)","college":"Alabama","college_conf":"Southeastern Conference","rookie_year":2018,"status":"A01","sr_id":"sr:player:1473910","draft":{"year":2018,"round":3,"number":93,"team":{"id":"f7ddd7fa-0bae-4f90-bc8e-669e4d6cf2de","name":"Jaguars","market":"Jacksonville","alias":"JAC","sr_id":"sr:competitor:4386"}},"references":[{"id":"46162","origin":"nflx"},{"id":"00-0034779","origin":"gsis"}]},{"id":"a21c5573-d9eb-4c4d-838a-12b63c513a1b","name":"Nick Harris","jersey":"53","last_name":"Harris","first_name":"Nick","abbr_name":"N.Harris","preferred_name":"Nick","birth_date":"1998-11-13","weight":302.0,"height":73,"position":"C","birth_place":"Inglewood, CA, USA","high_school":"JSerra Catholic (CA)","college":"Washington","college_conf":"Pacific Twelve Conference","rookie_year":2020,"status":"A01","sr_id":"sr:player:2040217","draft":{"year":2020,"round":5,"number":160,"team":{"id":"d5a2eb42-8065-4174-ab79-0a6fa820e35e","name":"Browns","market":"Cleveland","alias":"CLE","sr_id":"sr:competitor:4417"}},"references":[{"id":"00-0036236","origin":"gsis"},{"id":"52568","origin":"nflx"}]},{"id":"a5780ea2-376e-4187-8be1-7c7fd2d0a12f","name":"Brian Allen","jersey":"25","last_name":"Allen","first_name":"Brian","abbr_name":"B.Allen","preferred_name":"Brian","birth_date":"1993-10-21","weight":215.0,"height":75,"position":"CB","birth_place":"La Marque, TX, USA","high_school":"La Marque (TX)","college":"Utah","college_conf":"Pacific Twelve Conference","rookie_year":2017,"status":"A01","sr_id":"sr:player:1130063","draft":{"year":2017,"round":5,"number":173,"team":{"id":"cb2f9f1f-ac67-424e-9e72-1475cb0ed398","name":"Steelers","market":"Pittsburgh","alias":"PIT","sr_id":"sr:competitor:4345"}},"references":[{"id":"00-0033467","origin":"gsis"},{"id":"44986","origin":"nflx"}]},{"id":"a85a0ba9-674c-4f37-a944-474fc6cdf557","name":"Myles Garrett","jersey":"95","last_name":"Garrett","first_name":"Myles","abbr_name":"M.Garrett","preferred_name":"Myles","birth_date":"1995-12-29","weight":272.0,"height":76,"position":"DE","birth_place":"Arlington, TX, USA","high_school":"Arlington Martin (TX)","college":"Texas A&amp;M","college_conf":"Southeastern Conference","rookie_year":2017,"status":"A01","sr_id":"sr:player:1129517","draft":{"year":2017,"round":1,"number":1,"team":{"id":"d5a2eb42-8065-4174-ab79-0a6fa820e35e","name":"Browns","market":"Cleveland","alias":"CLE","sr_id":"sr:competitor:4417"}},"references":[{"id":"00-0033868","origin":"gsis"},{"id":"44813","origin":"nflx"}]},{"id":"a87f6156-c028-4634-84a8-e3388d6dff2b","name":"Kendall Lamm","jersey":"70","last_name":"Lamm","first_name":"Kendall","abbr_name":"K.Lamm","preferred_name":"Kendall","birth_date":"1992-06-05","weight":310.0,"height":77,"position":"T","birth_place":"Charlotte, NC, USA","high_school":"Butler (NC)","college":"Appalachian State","college_conf":"Sun Belt Conference","rookie_year":2015,"status":"A01","sr_id":"sr:player:835487","references":[{"id":"42952","origin":"nflx"},{"id":"00-0031921","origin":"gsis"}]},{"id":"aefdc3d3-0851-4782-b298-f06f137d42c9","name":"Denzel Ward","jersey":"21","last_name":"Ward","first_name":"Denzel","abbr_name":"D.Ward","preferred_name":"Denzel","birth_date":"1997-04-28","weight":191.0,"height":71,"position":"CB","birth_place":"Macedonia, OH, USA","high_school":"Macedonia Nordonia (OH)","college":"Ohio State","college_conf":"Big Ten Conference","rookie_year":2018,"status":"A01","sr_id":"sr:player:1218182","draft":{"year":2018,"round":1,"number":4,"team":{"id":"d5a2eb42-8065-4174-ab79-0a6fa820e35e","name":"Browns","market":"Cleveland","alias":"CLE","sr_id":"sr:competitor:4417"}},"references":[{"id":"46073","origin":"nflx"},{"id":"00-0034856","origin":"gsis"}]},{"id":"b220a72d-6870-418a-98af-ef50632be774","name":"Tae Davis","jersey":"55","last_name":"Davis","first_name":"Tae","abbr_name":"T.Davis","preferred_name":"Tae","birth_date":"1996-08-14","weight":224.0,"height":73,"position":"ILB","birth_place":"Oxford, AL, USA","high_school":"Oxford (AL)","college":"Chattanooga","college_conf":"Southern Conference","rookie_year":2018,"status":"A01","sr_id":"sr:player:1477898","references":[{"id":"46684","origin":"nflx"},{"id":"00-0034500","origin":"gsis"}]},{"id":"bc63567a-81e7-44c9-a85f-8aa9532ab4fd","name":"Jamie Gillan","jersey":"7","last_name":"Gillan","first_name":"Jamie","abbr_name":"J.Gillan","preferred_name":"Jamie","birth_date":"1997-07-04","weight":207.0,"height":73,"position":"P","birth_place":"Leonardtown, MD, USA","high_school":"Leonardtown (MD)","college":"Arkansas-Pine Bluff","college_conf":"Southwestern Athletic Conference","rookie_year":2019,"status":"A01","sr_id":"sr:player:1188190","references":[{"id":"48139","origin":"nflx"},{"id":"00-0035042","origin":"gsis"}]},{"id":"bcebf5f0-0224-4cc8-9a78-1aefd55bfc87","name":"Malcolm Smith","jersey":"56","last_name":"Smith","first_name":"Malcolm","abbr_name":"M.Smith","preferred_name":"Malcolm","birth_date":"1989-07-05","weight":225.0,"height":72,"position":"OLB","birth_place":"Woodland Hills, CA, USA","high_school":"Taft (CA)","college":"Southern California","college_conf":"Pacific Twelve Conference","rookie_year":2011,"status":"A01","sr_id":"sr:player:830379","draft":{"year":2011,"round":7,"number":242,"team":{"id":"3d08af9e-c767-4f88-a7dc-b920c6d2b4a8","name":"Seahawks","market":"Seattle","alias":"SEA","sr_id":"sr:competitor:4430"}},"references":[{"id":"37317","origin":"nflx"},{"id":"00-0028180","origin":"gsis"}]},{"id":"bd49c4a4-1314-45e1-bff5-fc67ba41d1dd","name":"Matt McCrane","jersey":"3","last_name":"McCrane","first_name":"Matthew","abbr_name":"M.McCrane","preferred_name":"Matthew","birth_date":"1994-09-08","weight":165.0,"height":70,"position":"K","birth_place":"Brownwood, TX, USA","high_school":"Brownwood (TX)","college":"Kansas State","college_conf":"Big Twelve Conference","rookie_year":2018,"status":"A01","sr_id":"sr:player:1476744","references":[{"id":"00-0034479","origin":"gsis"},{"id":"46663","origin":"nflx"}]},{"id":"bd4a07dd-aeae-4ae0-87e4-a8b65ad6870c","name":"George Obinna","jersey":"60","last_name":"Obinna","first_name":"George","abbr_name":"G.Obinna","preferred_name":"George","birth_date":"1996-08-23","weight":240.0,"height":75,"position":"DE","birth_place":"Tracy, CA, USA","high_school":"Tracy (CA)","college":"Sacramento State","college_conf":"Big Sky Conference","rookie_year":2020,"status":"A01","sr_id":"sr:player:1195142","references":[{"id":"00-0036119","origin":"gsis"},{"id":"53023","origin":"nflx"}]},{"id":"bdebbb66-ceff-4cc9-b74f-00e14be21530","name":"Anthony Fabiano","jersey":"58","last_name":"Fabiano","first_name":"Anthony","abbr_name":"A.Fabiano","preferred_name":"Anthony","birth_date":"1993-07-13","weight":303.0,"height":76,"position":"C","birth_place":"Wakefield, MA, USA","high_school":"Wakefield (MA)","college":"Harvard","college_conf":"Ivy League","rookie_year":2016,"status":"A01","sr_id":"sr:player:1073990","references":[{"id":"43687","origin":"nflx"},{"id":"00-0032567","origin":"gsis"}]},{"id":"bdeddbb2-2b56-4b46-915b-19eb71fbbe45","name":"Derrick Willies","jersey":"16","last_name":"Willies","first_name":"Derrick","abbr_name":"D.Willies","preferred_name":"Derrick","birth_date":"1994-10-17","weight":207.0,"height":76,"position":"WR","birth_place":"Banning, CA, USA","high_school":"Rock Island (IL)","college":"Texas Tech","college_conf":"Big Twelve Conference","rookie_year":2018,"status":"A01","sr_id":"sr:player:1475826","references":[{"id":"46511","origin":"nflx"},{"id":"00-0034258","origin":"gsis"}]},{"id":"bea5ccd6-b05b-43f8-975f-396399349a42","name":"Jovante Moffatt","jersey":"35","last_name":"Moffatt","first_name":"Jovante","abbr_name":"J.Moffatt","preferred_name":"Jovante","birth_date":"1996-12-25","weight":210.0,"height":72,"position":"SS","birth_place":"Union City, TN, USA","high_school":"Union City (TN)","college":"Middle Tennessee","college_conf":"Conference USA","rookie_year":2020,"status":"A01","sr_id":"sr:player:1190928","references":[{"id":"53022","origin":"nflx"},{"id":"00-0036118","origin":"gsis"}]},{"id":"c362b855-a313-4b46-ab26-a82082e1e8ee","name":"Elijah Lee","jersey":"52","last_name":"Lee","first_name":"Elijah","abbr_name":"E.Lee","preferred_name":"Elijah","birth_date":"1996-02-08","weight":229.0,"height":74,"position":"OLB","birth_place":"Blue Springs, MO, USA","high_school":"Blue Springs (MO)","college":"Kansas State","college_conf":"Big Twelve Conference","rookie_year":2017,"status":"A01","sr_id":"sr:player:1130193","draft":{"year":2017,"round":7,"number":232,"team":{"id":"33405046-04ee-4058-a950-d606f8c30852","name":"Vikings","market":"Minnesota","alias":"MIN","sr_id":"sr:competitor:4423"}},"references":[{"id":"45045","origin":"nflx"},{"id":"00-0033973","origin":"gsis"}]},{"id":"c5ae93f5-f293-4e9f-89a0-6d8bda64ee1e","name":"Michael Dunn","jersey":"68","last_name":"Dunn","first_name":"Michael","abbr_name":"M.Dunn","preferred_name":"Michael","birth_date":"1994-08-28","weight":307.0,"height":77,"position":"T","birth_place":"Bethesda, MD, USA","high_school":"Whitman (MD)","college":"Maryland","college_conf":"Big Ten Conference","rookie_year":2017,"status":"A01","sr_id":"sr:player:1231424","references":[{"id":"45798","origin":"nflx"},{"id":"00-0033995","origin":"gsis"}]},{"id":"d0780152-5d3e-4add-99bd-e330c258df10","name":"Alexander Hollins","jersey":"83","last_name":"Hollins","first_name":"Alexander","abbr_name":"A.Hollins","preferred_name":"Alexander","birth_date":"1996-11-24","weight":166.0,"height":73,"position":"WR","birth_place":"Yazoo City, MS, USA","high_school":"Yazoo County (MS)","college":"Eastern Illinois","college_conf":"Ohio Valley Conference","rookie_year":2019,"status":"A01","sr_id":"sr:player:1259152","references":[{"id":"48212","origin":"nflx"},{"id":"00-0035104","origin":"gsis"}]},{"id":"d0d2e26b-f5a7-4455-86b8-096508ac8eea","name":"Joe Jackson","jersey":"91","last_name":"Jackson","first_name":"Joe","abbr_name":"J.Jackson","preferred_name":"Joe","birth_date":"1996-12-20","weight":275.0,"height":76,"position":"DE","birth_place":"Homestead, FL, USA","high_school":"Gulliver Prep (FL)","college":"Miami","college_conf":"Atlantic Coast Conference","rookie_year":2019,"status":"A01","sr_id":"sr:player:1216980","draft":{"year":2019,"round":5,"number":165,"team":{"id":"e627eec7-bbae-4fa4-8e73-8e1d6bc5c060","name":"Cowboys","market":"Dallas","alias":"DAL","sr_id":"sr:competitor:4392"}},"references":[{"id":"47948","origin":"nflx"},{"id":"00-0035281","origin":"gsis"}]},{"id":"d11ad65e-9d24-4157-9f5b-ef8495bcc791","name":"Kyle Lauletta","jersey":"16","last_name":"Lauletta","first_name":"Kyle","abbr_name":"K.Lauletta","preferred_name":"Kyle","birth_date":"1995-03-17","weight":222.0,"height":74,"position":"QB","birth_place":"Exton, PA, USA","high_school":"Downingtown East (PA)","college":"Richmond","college_conf":"Colonial Athletic Association","rookie_year":2018,"status":"A01","sr_id":"sr:player:1229952","draft":{"year":2018,"round":4,"number":108,"team":{"id":"04aa1c9d-66da-489d-b16a-1dee3f2eec4d","name":"Giants","market":"New York","alias":"NYG","sr_id":"sr:competitor:4426"}},"references":[{"id":"46177","origin":"nflx"},{"id":"00-0034369","origin":"gsis"}]},{"id":"e1f9e986-6deb-4302-8478-eb64abe7aa24","name":"Colby Gossett","jersey":"71","last_name":"Gossett","first_name":"Colby","abbr_name":"C.Gossett","preferred_name":"Colby","birth_date":"1995-06-23","weight":331.0,"height":77,"position":"G","birth_place":"Cumming, GA, USA","high_school":"North Forsyth (GA)","college":"Appalachian State","college_conf":"Sun Belt Conference","rookie_year":2018,"status":"R62","sr_id":"sr:player:1218608","draft":{"year":2018,"round":6,"number":213,"team":{"id":"33405046-04ee-4058-a950-d606f8c30852","name":"Vikings","market":"Minnesota","alias":"MIN","sr_id":"sr:competitor:4423"}},"references":[{"id":"46282","origin":"nflx"},{"id":"00-0034165","origin":"gsis"}]},{"id":"e3a0e17e-fb75-4284-b89c-ddbc758f3d20","name":"Blake Hance","jersey":"62","last_name":"Hance","first_name":"Blake","abbr_name":"B.Hance","preferred_name":"Blake","birth_date":"1996-01-11","weight":310.0,"height":77,"position":"T","birth_place":"Jacksonville, IL, USA","high_school":"Jacksonville (IL)","college":"Northwestern","college_conf":"Big Ten Conference","rookie_year":2019,"status":"A01","sr_id":"sr:player:1222214","references":[{"id":"48485","origin":"nflx"},{"id":"00-0035355","origin":"gsis"}]},{"id":"eb904c68-f01b-4af3-9427-dd6a6c35511b","name":"Vincent Taylor","jersey":"96","last_name":"Taylor","first_name":"Vincent","abbr_name":"V.Taylor","preferred_name":"Vincent","birth_date":"1994-01-05","weight":311.0,"height":75,"position":"DT","birth_place":"New Orleans, LA, USA","high_school":"James Madison (TX)","college":"Oklahoma State","college_conf":"Big Twelve Conference","rookie_year":2017,"status":"A01","sr_id":"sr:player:1130229","draft":{"year":2017,"round":6,"number":194,"team":{"id":"4809ecb0-abd3-451d-9c4a-92a90b83ca06","name":"Dolphins","market":"Miami","alias":"MIA","sr_id":"sr:competitor:4287"}},"references":[{"id":"45007","origin":"nflx"},{"id":"00-0033469","origin":"gsis"}]},{"id":"f1236815-5ed7-4bab-808f-700c4516fd7d","name":"Ja'Marcus Bradley","jersey":"84","last_name":"Bradley","first_name":"Ja'Marcus","abbr_name":"J.Bradley","preferred_name":"Ja'Marcus","birth_date":"1996-12-11","weight":195.0,"height":73,"position":"WR","birth_place":"Ackerman, MS, USA","high_school":"Choctaw County (MS)","college":"Louisiana-Lafayette","college_conf":"Sun Belt Conference","rookie_year":2020,"status":"A01","sr_id":"sr:player:2040191","references":[{"id":"00-0036110","origin":"gsis"},{"id":"53014","origin":"nflx"}]},{"id":"f46e812f-14c6-4af8-9316-01a880adebc5","name":"D'Ernest Johnson","jersey":"30","last_name":"Johnson","first_name":"D'Ernest","abbr_name":"D.Johnson","preferred_name":"D'Ernest","birth_date":"1996-02-27","weight":208.0,"height":70,"position":"RB","birth_place":"Immokalee, FL, USA","high_school":"Immokalee (FL)","college":"South Florida","college_conf":"American Athletic Conference","rookie_year":2019,"status":"A01","sr_id":"sr:player:1853482","references":[{"id":"00-0035628","origin":"gsis"},{"id":"47605","origin":"nflx"}]},{"id":"f58a5899-8b78-46e8-a29a-ba6273b7d872","name":"Harrison Bryant","jersey":"88","last_name":"Bryant","first_name":"Harrison","abbr_name":"H.Bryant","preferred_name":"Harrison","birth_date":"1998-04-23","weight":240.0,"height":77,"position":"TE","birth_place":"Gray, GA, USA","high_school":"John Milledge Academy (GA)","college":"Florida Atlantic","college_conf":"Conference USA","rookie_year":2020,"status":"A01","sr_id":"sr:player:2040255","draft":{"year":2020,"round":4,"number":115,"team":{"id":"d5a2eb42-8065-4174-ab79-0a6fa820e35e","name":"Browns","market":"Cleveland","alias":"CLE","sr_id":"sr:competitor:4417"}},"references":[{"id":"52523","origin":"nflx"},{"id":"00-0036232","origin":"gsis"}]},{"id":"ffa1d197-25af-43a9-ae61-05ab20a0a5be","name":"Chris Hubbard","jersey":"74","last_name":"Hubbard","first_name":"Christopher","abbr_name":"C.Hubbard","preferred_name":"Christopher","birth_date":"1991-04-23","weight":295.0,"height":76,"position":"T","birth_place":"Columbus, GA, USA","high_school":"Carver (GA)","college":"Alabama-Birmingham","college_conf":"Conference USA","rookie_year":2013,"status":"A01","sr_id":"sr:player:829761","references":[{"id":"00-0029963","origin":"gsis"},{"id":"40416","origin":"nflx"}]}],"_comment":"Generation started @ 2021-02-12 17:54:21 UTC ended @ 2021-02-12 17:54:21 UTC"}