{"id":"3d08af9e-c767-4f88-a7dc-b920c6d2b4a8","name":"Seahawks","market":"Seattle","alias":"SEA","sr_id":"sr:competitor:4430","franchise":{"id":"a52ddba9-4709-4b76-8b1b-d9561607f7ec","name":"Seahawks","alias":"SEA","references":[{"id":"26","origin":"gsis"}]},"venue":{"id":"c6b9e5df-c9e4-434c-b3e6-83928f11cbda","name":"Lumen Field","city":"Seattle","state":"WA","country":"USA","zip":"98134","address":"800 Occidental Avenue South","capacity":68000,"surface":"artificial","roof_type":"outdoor","sr_id":"sr:venue:2291","location":{"lat":"47.595165","lng":"-122.331650"}},"division":{"id":"390d000d-9949-42e6-bf5e-b166dc463675","name":"NFC West","alias":"NFC_WEST"},"conference":{"id":"b1808e5f-d40b-47c0-8af8-5175c0fdcd26","name":"NFC","alias":"NFC"},"references":[{"id":"SEA","origin":"gsis"}],"coaches":[{"id":"0e95c151-6131-438a-bdde-da600d66f99f","full_name":"Ken Norton Jr.","first_name":"Ken","last_name":"Norton","position":"Defensive Coordinator"},{"id":"7f016ebd-3396-4adb-8ec6-20f4186c9c96","full_name":"Shane Waldron","first_name":"Shane","last_name":"Waldron","position":"Offensive Coordinator"},{"id":"8c74ff3b-c121-4d2c-9387-34f5900208a9","full_name":"Pete Carroll","first_name":"Pete","last_name":"Carroll","position":"Head Coach"}],"team_colors":[{"type":"primary","hex_color":"#002244","alpha":0.0,"rgb_color":{"red":0,"green":34,"blue":68}},{"type":"secondary","hex_color":"#69be28","alpha":0.0,"rgb_color":{"red":105,"green":190,"blue":40}}],"players":[{"id":"01d96b53-488d-4d98-8623-b2b29c7ebfbf","name":"Patrick Carr","jersey":"39","last_name":"Carr","first_name":"Patrick","abbr_name":"P.Carr","preferred_name":"Patrick","birth_date":"1995-09-22","weight":205.0,"height":70,"position":"RB","birth_place":"The Woodlands, TX, USA","high_school":"The Woodlands (TX)","college":"Houston","college_conf":"American Athletic Conference","rookie_year":2020,"status":"A01","sr_id":"sr:player:2040269","references":[{"id":"52957","origin":"nflx"},{"id":"00-0036054","origin":"gsis"}]},{"id":"03af0e0d-a443-4b09-9ab5-4f2695248346","name":"Damontre Moore","jersey":"99","last_name":"Moore","first_name":"Damontre","abbr_name":"D.Moore","preferred_name":"Damontre","birth_date":"1992-09-11","weight":260.0,"height":76,"position":"DE","birth_place":"DeSoto, TX, USA","high_school":"Rowlett (TX)","college":"Texas A&amp;M","college_conf":"Southeastern Conference","rookie_year":2013,"status":"A01","sr_id":"sr:player:828083","draft":{"year":2013,"round":3,"number":81,"team":{"id":"04aa1c9d-66da-489d-b16a-1dee3f2eec4d","name":"Giants","market":"New York","alias":"NYG","sr_id":"sr:competitor:4426"}},"references":[{"id":"00-0030069","origin":"gsis"},{"id":"40029","origin":"nflx"}]},{"id":"03f235b8-e338-450d-9107-8103b7d0a32d","name":"Phil Haynes","jersey":"60","last_name":"Haynes","first_name":"Phil","abbr_name":"P.Haynes","preferred_name":"Phil","birth_date":"1995-10-19","weight":322.0,"height":76,"position":"G","birth_place":"Raleigh, NC, USA","high_school":"Raleigh Enloe (NC)","college":"Wake Forest","college_conf":"Atlantic Coast Conference","rookie_year":2019,"status":"A01","sr_id":"sr:player:1734863","draft":{"year":2019,"round":4,"number":124,"team":{"id":"3d08af9e-c767-4f88-a7dc-b920c6d2b4a8","name":"Seahawks","market":"Seattle","alias":"SEA","sr_id":"sr:competitor:4430"}},"references":[{"id":"47907","origin":"nflx"},{"id":"00-0035141","origin":"gsis"}]},{"id":"09b78e4f-e683-4c5d-b35e-35cc0dbbf7e5","name":"Poona Ford","jersey":"97","last_name":"Ford","first_name":"Poona","abbr_name":"P.Ford","preferred_name":"Poona","birth_date":"1995-11-19","weight":310.0,"height":71,"position":"NT","birth_place":"Hilton Head, SC, USA","high_school":"Hilton Head (SC)","college":"Texas","college_conf":"Big Twelve Conference","rookie_year":2018,"status":"A01","sr_id":"sr:player:1221158","references":[{"id":"00-0034234","origin":"gsis"},{"id":"46487","origin":"nflx"}]},{"id":"0afca88b-83e7-49d6-80df-1f68b21cca9f","name":"Chris Carson","jersey":"32","last_name":"Carson","first_name":"Chris","abbr_name":"C.Carson","preferred_name":"Chris","birth_date":"1994-09-16","weight":222.0,"height":71,"position":"RB","birth_place":"Biloxi, MS, USA","high_school":"Parkview (GA)","college":"Oklahoma State","college_conf":"Big Twelve Conference","rookie_year":2017,"status":"A01","sr_id":"sr:player:1130199","draft":{"year":2017,"round":7,"number":249,"team":{"id":"3d08af9e-c767-4f88-a7dc-b920c6d2b4a8","name":"Seahawks","market":"Seattle","alias":"SEA","sr_id":"sr:competitor:4430"}},"references":[{"id":"45062","origin":"nflx"},{"id":"00-0033594","origin":"gsis"}]},{"id":"1163ba47-560b-4705-82be-69967c4fc096","name":"Linden Stephens","jersey":"34","last_name":"Stephens","first_name":"Linden","abbr_name":"L.Stephens","preferred_name":"Linden","birth_date":"1995-03-21","weight":193.0,"height":72,"position":"DB","birth_place":"Euclid, OH, USA","high_school":"Euclid (OH)","college":"Cincinnati","college_conf":"American Athletic Conference","rookie_year":2018,"status":"A01","sr_id":"sr:player:1193106","references":[{"id":"00-0034130","origin":"gsis"},{"id":"46392","origin":"nflx"}]},{"id":"16c67c97-ffd9-4f92-917d-ad6124ce1f6e","name":"Luke Willson","jersey":"82","last_name":"Willson","first_name":"Luke","abbr_name":"L.Willson","preferred_name":"Luke","birth_date":"1990-01-15","weight":254.0,"height":77,"position":"TE","birth_place":"LaSalle, ON, CAN","high_school":"St. Thomas of Villanova (CAN)","college":"Rice","college_conf":"Conference USA","rookie_year":2013,"status":"A01","sr_id":"sr:player:829759","draft":{"year":2013,"round":5,"number":158,"team":{"id":"3d08af9e-c767-4f88-a7dc-b920c6d2b4a8","name":"Seahawks","market":"Seattle","alias":"SEA","sr_id":"sr:competitor:4430"}},"references":[{"id":"00-0030089","origin":"gsis"},{"id":"40106","origin":"nflx"}]},{"id":"16da963d-a300-4d72-8e4d-7771196c03e9","name":"Cody Thompson","jersey":"81","last_name":"Thompson","first_name":"Cody","abbr_name":"C.Thompson","preferred_name":"Cody","birth_date":"1996-01-11","weight":205.0,"height":74,"position":"WR","birth_place":"Huron, OH, USA","high_school":"Huron (OH)","college":"Toledo","college_conf":"Mid-American Conference","rookie_year":2019,"status":"A01","sr_id":"sr:player:1229300","references":[{"id":"48266","origin":"nflx"},{"id":"00-0035164","origin":"gsis"}]},{"id":"17664e93-8236-4eb0-9505-4e71f43b5a7d","name":"D.J. Reed Jr.","jersey":"29","last_name":"Reed","first_name":"D.J.","abbr_name":"D.Reed","preferred_name":"D.J.","birth_date":"1996-11-11","weight":188.0,"height":69,"position":"FS","birth_place":"Bakersfield, CA, USA","high_school":"Independence (CA)","college":"Kansas State","college_conf":"Big Twelve Conference","rookie_year":2018,"status":"A01","sr_id":"sr:player:1225400","name_suffix":"Jr.","draft":{"year":2018,"round":5,"number":142,"team":{"id":"f0e724b0-4cbf-495a-be47-013907608da9","name":"49ers","market":"San Francisco","alias":"SF","sr_id":"sr:competitor:4389"}},"references":[{"id":"46211","origin":"nflx"},{"id":"00-0034384","origin":"gsis"}]},{"id":"1a92b0ad-3eb2-4df3-bf02-04c4d9ffe10c","name":"Jamal Adams","jersey":"33","last_name":"Adams","first_name":"Jamal","abbr_name":"J.Adams","preferred_name":"Jamal","birth_date":"1995-10-17","weight":213.0,"height":73,"position":"SS","birth_place":"Lewisville, TX, USA","high_school":"Carrollton Hebron (TX)","college":"Louisiana State","college_conf":"Southeastern Conference","rookie_year":2017,"status":"A01","sr_id":"sr:player:1129509","draft":{"year":2017,"round":1,"number":6,"team":{"id":"5fee86ae-74ab-4bdd-8416-42a9dd9964f3","name":"Jets","market":"New York","alias":"NYJ","sr_id":"sr:competitor:4427"}},"references":[{"id":"44818","origin":"nflx"},{"id":"00-0033872","origin":"gsis"}]},{"id":"1c468a8a-355f-429a-a12d-d8528fdc6aa2","name":"Marquise Blair","jersey":"27","last_name":"Blair","first_name":"Marquise","abbr_name":"M.Blair","preferred_name":"Marquise","birth_date":"1997-07-18","weight":195.0,"height":74,"position":"FS","birth_place":"Wooster, OH, USA","high_school":"Wooster (OH)","college":"Utah","college_conf":"Pacific Twelve Conference","rookie_year":2019,"status":"A01","sr_id":"sr:player:1231406","draft":{"year":2019,"round":2,"number":47,"team":{"id":"3d08af9e-c767-4f88-a7dc-b920c6d2b4a8","name":"Seahawks","market":"Seattle","alias":"SEA","sr_id":"sr:competitor:4430"}},"references":[{"id":"47830","origin":"nflx"},{"id":"00-0035139","origin":"gsis"}]},{"id":"1ea7affb-e5e7-491a-aaa3-55e200b2eb48","name":"Colby Parkinson","jersey":"84","last_name":"Parkinson","first_name":"Colby","abbr_name":"C.Parkinson","preferred_name":"Colby","birth_date":"1999-01-08","weight":251.0,"height":79,"position":"TE","birth_place":"Simi Valley, CA, USA","high_school":"Oaks Christian (CA)","college":"Stanford","college_conf":"Pacific Twelve Conference","rookie_year":2020,"status":"A01","sr_id":"sr:player:2040111","draft":{"year":2020,"round":4,"number":133,"team":{"id":"3d08af9e-c767-4f88-a7dc-b920c6d2b4a8","name":"Seahawks","market":"Seattle","alias":"SEA","sr_id":"sr:competitor:4430"}},"references":[{"id":"00-0036244","origin":"gsis"},{"id":"52541","origin":"nflx"}]},{"id":"21199f7c-91bc-4295-a6c8-bc0cfd017616","name":"Branden Jackson","jersey":"93","last_name":"Jackson","first_name":"Branden","abbr_name":"B.Jackson","preferred_name":"Branden","birth_date":"1992-11-11","weight":295.0,"height":76,"position":"DE","birth_place":"McKeesport, PA, USA","high_school":"McKeesport (PA)","college":"Texas Tech","college_conf":"Big Twelve Conference","rookie_year":2016,"status":"A01","sr_id":"sr:player:1074008","references":[{"id":"44044","origin":"nflx"},{"id":"00-0033024","origin":"gsis"}]},{"id":"2b119688-83b5-4d19-acbf-fa2087035fae","name":"Rashaad Penny","jersey":"20","last_name":"Penny","first_name":"Rashaad","abbr_name":"R.Penny","preferred_name":"Rashaad","birth_date":"1996-02-02","weight":220.0,"height":71,"position":"RB","birth_place":"Norwalk, CA, USA","high_school":"Norwalk (CA)","college":"San Diego State","college_conf":"Mountain West Conference","rookie_year":2018,"status":"A01","sr_id":"sr:player:1473410","draft":{"year":2018,"round":1,"number":27,"team":{"id":"3d08af9e-c767-4f88-a7dc-b920c6d2b4a8","name":"Seahawks","market":"Seattle","alias":"SEA","sr_id":"sr:competitor:4430"}},"references":[{"id":"00-0034750","origin":"gsis"},{"id":"46096","origin":"nflx"}]},{"id":"383f4814-6836-4766-a297-fc063e8509cc","name":"Will Dissly","jersey":"89","last_name":"Dissly","first_name":"Will","abbr_name":"W.Dissly","preferred_name":"Will","birth_date":"1996-07-08","weight":267.0,"height":76,"position":"TE","birth_place":"Bozeman, MT, USA","high_school":"Bozeman (MT)","college":"Washington","college_conf":"Pacific Twelve Conference","rookie_year":2018,"status":"A01","sr_id":"sr:player:1479142","draft":{"year":2018,"round":4,"number":120,"team":{"id":"3d08af9e-c767-4f88-a7dc-b920c6d2b4a8","name":"Seahawks","market":"Seattle","alias":"SEA","sr_id":"sr:competitor:4430"}},"references":[{"id":"00-0034159","origin":"gsis"},{"id":"46189","origin":"nflx"}]},{"id":"3a29784c-832f-4e41-a4ac-71d4f9ad410c","name":"Carlos Hyde","jersey":"30","last_name":"Hyde","first_name":"Carlos","abbr_name":"C.Hyde","preferred_name":"Carlos","birth_date":"1990-09-20","weight":229.0,"height":72,"position":"RB","birth_place":"Cincinnati, OH, USA","high_school":"Naples (FL)","college":"Ohio State","college_conf":"Big Ten Conference","rookie_year":2014,"status":"A01","sr_id":"sr:player:829661","draft":{"year":2014,"round":2,"number":57,"team":{"id":"f0e724b0-4cbf-495a-be47-013907608da9","name":"49ers","market":"San Francisco","alias":"SF","sr_id":"sr:competitor:4389"}},"references":[{"id":"41286","origin":"nflx"},{"id":"00-0031045","origin":"gsis"}]},{"id":"409d4cac-ee90-4470-9710-ebe671678339","name":"Russell Wilson","jersey":"3","last_name":"Wilson","first_name":"Russell","abbr_name":"R.Wilson","preferred_name":"Russell","birth_date":"1988-11-29","weight":215.0,"height":71,"position":"QB","birth_place":"Richmond, VA, USA","high_school":"Collegiate (VA)","college":"Wisconsin","college_conf":"Big Ten Conference","rookie_year":2012,"status":"A01","sr_id":"sr:player:831309","draft":{"year":2012,"round":3,"number":75,"team":{"id":"3d08af9e-c767-4f88-a7dc-b920c6d2b4a8","name":"Seahawks","market":"Seattle","alias":"SEA","sr_id":"sr:competitor:4430"}},"references":[{"id":"00-0029263","origin":"gsis"},{"id":"38605","origin":"nflx"}]},{"id":"46664226-53c3-4ef9-9aeb-f708e3e8269f","name":"Mike Iupati","jersey":"70","last_name":"Iupati","first_name":"Mike","abbr_name":"M.Iupati","preferred_name":"Mike","birth_date":"1987-05-12","weight":331.0,"height":77,"position":"G","birth_place":"Vaitogi,, ASM","high_school":"Western (CA)","college":"Idaho","college_conf":"Western Athletic Conference","rookie_year":2010,"status":"A01","sr_id":"sr:player:829157","draft":{"year":2010,"round":1,"number":17,"team":{"id":"f0e724b0-4cbf-495a-be47-013907608da9","name":"49ers","market":"San Francisco","alias":"SF","sr_id":"sr:competitor:4389"}},"references":[{"id":"35456","origin":"nflx"},{"id":"00-0027869","origin":"gsis"}]},{"id":"475aa381-25d7-4d6e-a6ce-bc7601f4b034","name":"Damien Lewis","jersey":"68","last_name":"Lewis","first_name":"Damien","abbr_name":"D.Lewis","preferred_name":"Damien","birth_date":"1997-03-21","weight":332.0,"height":75,"position":"G","birth_place":"Canton, MS, USA","high_school":"Canton (MS)","college":"Louisiana State","college_conf":"Southeastern Conference","rookie_year":2020,"status":"A01","sr_id":"sr:player:2040041","draft":{"year":2020,"round":3,"number":69,"team":{"id":"3d08af9e-c767-4f88-a7dc-b920c6d2b4a8","name":"Seahawks","market":"Seattle","alias":"SEA","sr_id":"sr:competitor:4430"}},"references":[{"id":"00-0036417","origin":"gsis"},{"id":"52477","origin":"nflx"}]},{"id":"48ef5bfa-7b91-4ed1-ad12-e94c0bc101c2","name":"DeeJay Dallas","jersey":"31","last_name":"Dallas","first_name":"DeeJay","abbr_name":"D.Dallas","preferred_name":"DeeJay","birth_date":"1998-09-16","weight":214.0,"height":70,"position":"RB","birth_place":"Brunswick, GA, USA","high_school":"Glynn Academy (GA)","college":"Miami","college_conf":"Atlantic Coast Conference","rookie_year":2020,"status":"A01","sr_id":"sr:player:1232822","draft":{"year":2020,"round":4,"number":144,"team":{"id":"3d08af9e-c767-4f88-a7dc-b920c6d2b4a8","name":"Seahawks","market":"Seattle","alias":"SEA","sr_id":"sr:competitor:4430"}},"references":[{"id":"52552","origin":"nflx"},{"id":"00-0036425","origin":"gsis"}]},{"id":"4afb77d8-4564-469b-be4c-5a8587df8046","name":"Travis Homer","jersey":"25","last_name":"Homer","first_name":"Travis","abbr_name":"T.Homer","preferred_name":"Travis","birth_date":"1998-08-07","weight":202.0,"height":70,"position":"RB","birth_place":"West Palm Beach, FL, USA","high_school":"Oxbridge Academy (FL)","college":"Miami","college_conf":"Atlantic Coast Conference","rookie_year":2019,"status":"A01","sr_id":"sr:player:1217364","draft":{"year":2019,"round":6,"number":204,"team":{"id":"3d08af9e-c767-4f88-a7dc-b920c6d2b4a8","name":"Seahawks","market":"Seattle","alias":"SEA","sr_id":"sr:competitor:4430"}},"references":[{"id":"00-0035594","origin":"gsis"},{"id":"47987","origin":"nflx"}]},{"id":"5670f3dd-822d-4d13-a6c9-f981354441fc","name":"Darrell Taylor","jersey":"58","last_name":"Taylor","first_name":"Darrell","abbr_name":"D.Taylor","preferred_name":"Darrell","birth_date":"1997-03-24","weight":253.0,"height":75,"position":"DE","birth_place":"Hopewell, VA, USA","high_school":"Hopewell (VA)","college":"Tennessee","college_conf":"Southeastern Conference","rookie_year":2020,"status":"A01","sr_id":"sr:player:2040223","draft":{"year":2020,"round":2,"number":48,"team":{"id":"3d08af9e-c767-4f88-a7dc-b920c6d2b4a8","name":"Seahawks","market":"Seattle","alias":"SEA","sr_id":"sr:competitor:4430"}},"references":[{"id":"52456","origin":"nflx"},{"id":"00-0036413","origin":"gsis"}]},{"id":"577dfac0-3f0b-45ee-afff-c851c6aebb1e","name":"Cody Barton","jersey":"57","last_name":"Barton","first_name":"Cody","abbr_name":"C.Barton","preferred_name":"Cody","birth_date":"1996-11-13","weight":237.0,"height":74,"position":"MLB","birth_place":"Salt Lake City, UT, USA","high_school":"Brighton (UT)","college":"Utah","college_conf":"Pacific Twelve Conference","rookie_year":2019,"status":"A01","sr_id":"sr:player:1227342","draft":{"year":2019,"round":3,"number":88,"team":{"id":"3d08af9e-c767-4f88-a7dc-b920c6d2b4a8","name":"Seahawks","market":"Seattle","alias":"SEA","sr_id":"sr:competitor:4430"}},"references":[{"id":"47871","origin":"nflx"},{"id":"00-0035672","origin":"gsis"}]},{"id":"587d0a98-7ec5-45a5-adba-8af26e8f256b","name":"Greg Olsen","jersey":"88","last_name":"Olsen","first_name":"Greg","abbr_name":"G.Olsen","preferred_name":"Greg","birth_date":"1985-03-11","weight":255.0,"height":77,"position":"TE","birth_place":"Paterson, NJ, USA","high_school":"Wayne Hills (NJ)","college":"Miami","college_conf":"Atlantic Coast Conference","rookie_year":2007,"status":"A01","sr_id":"sr:player:828543","draft":{"year":2007,"round":1,"number":31,"team":{"id":"7b112545-38e6-483c-a55c-96cf6ee49cb8","name":"Bears","market":"Chicago","alias":"CHI","sr_id":"sr:competitor:4391"}},"references":[{"id":"32224","origin":"nflx"},{"id":"00-0025418","origin":"gsis"}]},{"id":"67c2f38f-b568-4bcf-a40f-750cef707a05","name":"Ryan Neal","jersey":"35","last_name":"Neal","first_name":"Ryan","abbr_name":"R.Neal","preferred_name":"Ryan","birth_date":"1995-12-24","weight":200.0,"height":75,"position":"CB","birth_place":"Hammond, IN, USA","high_school":"Merrillville (IN)","college":"Southern Illinois","college_conf":"Missouri Valley Football Conference","rookie_year":2018,"status":"A01","sr_id":"sr:player:1206928","references":[{"id":"00-0034527","origin":"gsis"},{"id":"46711","origin":"nflx"}]},{"id":"6fc3f73e-9c19-41cf-aa95-df4d83e29e9e","name":"Bruce Irvin","jersey":"51","last_name":"Irvin","first_name":"Bruce","abbr_name":"B.Irvin","preferred_name":"Bruce","birth_date":"1987-11-01","weight":250.0,"height":75,"position":"OLB","birth_place":"Atlanta, GA, USA","high_school":"Stephenson (GA)","college":"West Virginia","college_conf":"Big East","rookie_year":2012,"status":"A01","sr_id":"sr:player:829997","draft":{"year":2012,"round":1,"number":15,"team":{"id":"3d08af9e-c767-4f88-a7dc-b920c6d2b4a8","name":"Seahawks","market":"Seattle","alias":"SEA","sr_id":"sr:competitor:4430"}},"references":[{"id":"38545","origin":"nflx"},{"id":"00-0029193","origin":"gsis"}]},{"id":"704cc12d-78b1-482a-bd2e-06dc9a633ceb","name":"Jordan Simmons","jersey":"66","last_name":"Simmons","first_name":"Jordan","abbr_name":"J.Simmons","preferred_name":"Jordan","birth_date":"1994-07-15","weight":339.0,"height":76,"position":"G","birth_place":"Inglewood, CA, USA","high_school":"Crespi (CA)","college":"Southern California","college_conf":"Pacific Twelve Conference","rookie_year":2017,"status":"A01","sr_id":"sr:player:1136025","references":[{"id":"00-0033446","origin":"gsis"},{"id":"45346","origin":"nflx"}]},{"id":"706bc0ab-7200-47e9-9b09-726110eb83dc","name":"Bobby Wagner","jersey":"54","last_name":"Wagner","first_name":"Bobby","abbr_name":"B.Wagner","preferred_name":"Bobby","birth_date":"1990-06-27","weight":242.0,"height":72,"position":"MLB","birth_place":"Ontario, CA, USA","high_school":"Colony (CA)","college":"Utah State","college_conf":"Western Athletic Conference","rookie_year":2012,"status":"A01","sr_id":"sr:player:828039","draft":{"year":2012,"round":2,"number":47,"team":{"id":"3d08af9e-c767-4f88-a7dc-b920c6d2b4a8","name":"Seahawks","market":"Seattle","alias":"SEA","sr_id":"sr:competitor:4430"}},"references":[{"id":"38577","origin":"nflx"},{"id":"00-0029255","origin":"gsis"}]},{"id":"736c12de-b7be-4c12-bed2-57856b7c8449","name":"Ethan Pocic","jersey":"77","last_name":"Pocic","first_name":"Ethan","abbr_name":"E.Pocic","preferred_name":"Ethan","birth_date":"1995-08-05","weight":320.0,"height":78,"position":"C","birth_place":"Lemont, IL, USA","high_school":"Lemont (IL)","college":"Louisiana State","college_conf":"Southeastern Conference","rookie_year":2017,"status":"A01","sr_id":"sr:player:1129861","draft":{"year":2017,"round":2,"number":58,"team":{"id":"3d08af9e-c767-4f88-a7dc-b920c6d2b4a8","name":"Seahawks","market":"Seattle","alias":"SEA","sr_id":"sr:competitor:4430"}},"references":[{"id":"44870","origin":"nflx"},{"id":"00-0033901","origin":"gsis"}]},{"id":"73c958ee-0d55-49e9-a613-f4475b444fd5","name":"Tre Flowers","jersey":"21","last_name":"Flowers","first_name":"Tre","abbr_name":"T.Flowers","preferred_name":"Tre","birth_date":"1995-06-02","weight":203.0,"height":75,"position":"CB","birth_place":"Converse, TX, USA","high_school":"Judson (TX)","college":"Oklahoma State","college_conf":"Big Twelve Conference","rookie_year":2018,"status":"A01","sr_id":"sr:player:1475128","draft":{"year":2018,"round":5,"number":146,"team":{"id":"3d08af9e-c767-4f88-a7dc-b920c6d2b4a8","name":"Seahawks","market":"Seattle","alias":"SEA","sr_id":"sr:competitor:4430"}},"references":[{"id":"46215","origin":"nflx"},{"id":"00-0034756","origin":"gsis"}]},{"id":"7483724a-dfce-4d6f-b499-481d37744fee","name":"Tommy Champion","jersey":"79","last_name":"Champion","first_name":"Tommy","abbr_name":"T.Champion","preferred_name":"Tommy","birth_date":"1997-03-04","weight":320.0,"height":77,"position":"T","birth_place":"Jackson, MS, USA","high_school":"Copiah-Lincoln (MS)","college":"Mississippi State","college_conf":"Southeastern Conference","rookie_year":2020,"status":"A01","sr_id":"sr:player:1235862","references":[{"id":"52888","origin":"nflx"},{"id":"00-0035986","origin":"gsis"}]},{"id":"754faf0f-40f7-45f0-b23b-6ce990ecaf26","name":"D.K. Metcalf","jersey":"14","last_name":"Metcalf","first_name":"DK","abbr_name":"D.Metcalf","preferred_name":"DK","birth_date":"1997-12-14","weight":230.0,"height":76,"position":"WR","birth_place":"Oxford, MS, USA","high_school":"Oxford (MS)","college":"Mississippi","college_conf":"Southeastern Conference","rookie_year":2019,"status":"A01","sr_id":"sr:player:1230010","draft":{"year":2019,"round":2,"number":64,"team":{"id":"3d08af9e-c767-4f88-a7dc-b920c6d2b4a8","name":"Seahawks","market":"Seattle","alias":"SEA","sr_id":"sr:competitor:4430"}},"references":[{"id":"00-0035640","origin":"gsis"},{"id":"47847","origin":"nflx"}]},{"id":"7af4c94b-529b-4403-ab66-2bfed3fcf0c7","name":"Jason Myers","jersey":"5","last_name":"Myers","first_name":"Jason","abbr_name":"J.Myers","preferred_name":"Jason","birth_date":"1991-05-12","weight":190.0,"height":70,"position":"K","birth_place":"Chula Vista, CA, USA","high_school":"Mater Dei Catholic (CA)","college":"Marist","college_conf":"Pioneer Football League","rookie_year":2015,"status":"A01","sr_id":"sr:player:855698","references":[{"id":"00-0031492","origin":"gsis"},{"id":"41175","origin":"nflx"}]},{"id":"7c7d286f-5c3f-4fe1-864d-9351499bd530","name":"Shaquem Griffin","jersey":"49","last_name":"Griffin","first_name":"Shaquem","abbr_name":"S.Griffin","preferred_name":"Shaquem","birth_date":"1995-07-20","weight":229.0,"height":72,"position":"OLB","birth_place":"St. Petersburg, FL, USA","high_school":"Lakewood (FL)","college":"Central Florida","college_conf":"American Athletic Conference","rookie_year":2018,"status":"A01","sr_id":"sr:player:1475036","draft":{"year":2018,"round":5,"number":141,"team":{"id":"3d08af9e-c767-4f88-a7dc-b920c6d2b4a8","name":"Seahawks","market":"Seattle","alias":"SEA","sr_id":"sr:competitor:4430"}},"references":[{"id":"46210","origin":"nflx"},{"id":"00-0034755","origin":"gsis"}]},{"id":"7c84bbbd-6bc1-4d3a-8fe9-263b807a08b2","name":"Jamarco Jones","jersey":"73","last_name":"Jones","first_name":"Jamarco","abbr_name":"J.Jones","preferred_name":"Jamarco","birth_date":"1996-06-04","weight":293.0,"height":76,"position":"T","birth_place":"Chicago, IL, USA","high_school":"De La Salle (IL)","college":"Ohio State","college_conf":"Big Ten Conference","rookie_year":2018,"status":"A01","sr_id":"sr:player:1523293","draft":{"year":2018,"round":5,"number":168,"team":{"id":"3d08af9e-c767-4f88-a7dc-b920c6d2b4a8","name":"Seahawks","market":"Seattle","alias":"SEA","sr_id":"sr:competitor:4430"}},"references":[{"id":"00-0034729","origin":"gsis"},{"id":"46237","origin":"nflx"}]},{"id":"7dcdf083-2f41-4788-a668-000cbfd1c8b1","name":"Cedrick Lattimore","jersey":"65","last_name":"Lattimore","first_name":"Cedrick","abbr_name":"C.Lattimore","preferred_name":"Cedrick","birth_date":"1998-02-06","weight":295.0,"height":75,"position":"DT","birth_place":"Redford, MI, USA","high_school":"East English Village Prep (MI)","college":"Iowa","college_conf":"Big Ten Conference","rookie_year":2020,"status":"A01","sr_id":"sr:player:2040457","references":[{"id":"52961","origin":"nflx"},{"id":"00-0036058","origin":"gsis"}]},{"id":"8092ffd3-3f39-43eb-a602-b14fff77d413","name":"Quandre Diggs","jersey":"37","last_name":"Diggs","first_name":"Quandre","abbr_name":"Q.Diggs","preferred_name":"Quandre","birth_date":"1993-01-22","weight":197.0,"height":69,"position":"FS","birth_place":"Angleton, TX, USA","high_school":"Angleton (TX)","college":"Texas","college_conf":"Big Twelve Conference","rookie_year":2015,"status":"A01","sr_id":"sr:player:835115","draft":{"year":2015,"round":6,"number":200,"team":{"id":"c5a59daa-53a7-4de0-851f-fb12be893e9e","name":"Lions","market":"Detroit","alias":"DET","sr_id":"sr:competitor:4419"}},"references":[{"id":"42543","origin":"nflx"},{"id":"00-0031608","origin":"gsis"}]},{"id":"81997ce2-9e70-4014-999a-25ebb405dbf6","name":"Freddie Swain","jersey":"18","last_name":"Swain","first_name":"Freddie","abbr_name":"F.Swain","preferred_name":"Freddie","birth_date":"1998-08-04","weight":199.0,"height":72,"position":"WR","birth_place":"Ocala, FL, USA","high_school":"North Marion (FL)","college":"Florida","college_conf":"Southeastern Conference","rookie_year":2020,"status":"A01","sr_id":"sr:player:2040493","draft":{"year":2020,"round":6,"number":214,"team":{"id":"3d08af9e-c767-4f88-a7dc-b920c6d2b4a8","name":"Seahawks","market":"Seattle","alias":"SEA","sr_id":"sr:competitor:4430"}},"references":[{"id":"00-0036247","origin":"gsis"},{"id":"52622","origin":"nflx"}]},{"id":"83ffd861-ffb0-4560-a79c-52acd2b6cb1e","name":"Kyle Fuller","jersey":"61","last_name":"Fuller","first_name":"Kyle","abbr_name":"K.Fuller","preferred_name":"Kyle","birth_date":"1994-03-04","weight":320.0,"height":77,"position":"G","birth_place":"Duncanville, TX, USA","high_school":"Wylie (TX)","college":"Baylor","college_conf":"Big Twelve Conference","rookie_year":2017,"status":"A01","sr_id":"sr:player:1130151","draft":{"year":2017,"round":7,"number":243,"team":{"id":"82d2d380-3834-4938-835f-aec541e5ece7","name":"Texans","market":"Houston","alias":"HOU","sr_id":"sr:competitor:4324"}},"references":[{"id":"45056","origin":"nflx"},{"id":"00-0033592","origin":"gsis"}]},{"id":"872bbe18-ea66-415c-b556-6d15bda05b0e","name":"Quinton Dunbar","jersey":"22","last_name":"Dunbar","first_name":"Quinton","abbr_name":"Q.Dunbar","preferred_name":"Quinton","birth_date":"1992-07-22","weight":202.0,"height":74,"position":"CB","birth_place":"Miami, FL, USA","high_school":"Booker T. Washington (FL)","college":"Florida","college_conf":"Southeastern Conference","rookie_year":2015,"status":"A01","sr_id":"sr:player:855172","references":[{"id":"00-0032007","origin":"gsis"},{"id":"43008","origin":"nflx"}]},{"id":"8d77a320-4b95-498b-ba8e-f1db36f033cb","name":"Brad Lundblade","jersey":"64","last_name":"Lundblade","first_name":"Brad","abbr_name":"B.Lundblade","preferred_name":"Brad","birth_date":"1995-09-21","weight":305.0,"height":75,"position":"C","birth_place":"Nashville, TN, USA","high_school":"Liberty Christian (TX)","college":"Oklahoma State","college_conf":"Big Twelve Conference","rookie_year":2018,"status":"A01","sr_id":"sr:player:1477766","references":[{"id":"00-0034239","origin":"gsis"},{"id":"46492","origin":"nflx"}]},{"id":"8fe853ae-184e-4c65-a00e-70d2f141504f","name":"Ben Burr-Kirven","jersey":"55","last_name":"Burr-Kirven","first_name":"Ben","abbr_name":"B.Burr-Kirven","preferred_name":"Ben","birth_date":"1997-09-08","weight":230.0,"height":72,"position":"OLB","birth_place":"Menlo Park, CA, USA","high_school":"Sacred Heart Prep (CA)","college":"Washington","college_conf":"Pacific Twelve Conference","rookie_year":2019,"status":"A01","sr_id":"sr:player:1221618","draft":{"year":2019,"round":5,"number":142,"team":{"id":"3d08af9e-c767-4f88-a7dc-b920c6d2b4a8","name":"Seahawks","market":"Seattle","alias":"SEA","sr_id":"sr:competitor:4430"}},"references":[{"id":"00-0035143","origin":"gsis"},{"id":"47925","origin":"nflx"}]},{"id":"93ff0e6f-fee3-41d1-a913-6111cd9ebef1","name":"K.J. Wright","jersey":"50","last_name":"Wright","first_name":"K.J.","abbr_name":"K.Wright","preferred_name":"K.J.","birth_date":"1989-07-23","weight":246.0,"height":76,"position":"OLB","birth_place":"Memphis, TN, USA","high_school":"Olive Branch (MS)","college":"Mississippi State","college_conf":"Southeastern Conference","rookie_year":2011,"status":"A01","sr_id":"sr:player:828335","draft":{"year":2011,"round":4,"number":99,"team":{"id":"3d08af9e-c767-4f88-a7dc-b920c6d2b4a8","name":"Seahawks","market":"Seattle","alias":"SEA","sr_id":"sr:competitor:4430"}},"references":[{"id":"37174","origin":"nflx"},{"id":"00-0028037","origin":"gsis"}]},{"id":"9448aee3-538c-4ff3-8781-bc848b086bfc","name":"Ugo Amadi","jersey":"28","last_name":"Amadi","first_name":"Ugochukwu","abbr_name":"U.Amadi","preferred_name":"Ugochukwu","birth_date":"1997-05-16","weight":201.0,"height":69,"position":"FS","birth_place":"Nashville, TN, USA","high_school":"Overton (TN)","college":"Oregon","college_conf":"Pacific Twelve Conference","rookie_year":2019,"status":"A01","sr_id":"sr:player:1188748","draft":{"year":2019,"round":4,"number":132,"team":{"id":"3d08af9e-c767-4f88-a7dc-b920c6d2b4a8","name":"Seahawks","market":"Seattle","alias":"SEA","sr_id":"sr:competitor:4430"}},"references":[{"id":"00-0035142","origin":"gsis"},{"id":"47915","origin":"nflx"}]},{"id":"9912fa7a-040d-40cf-99b5-0a7a28e0ba1a","name":"Rasheem Green","jersey":"94","last_name":"Green","first_name":"Rasheem","abbr_name":"R.Green","preferred_name":"Rasheem","birth_date":"1997-05-15","weight":279.0,"height":76,"position":"DE","birth_place":"Los Angeles, CA, USA","high_school":"Junipero Serra (CA)","college":"Southern California","college_conf":"Pacific Twelve Conference","rookie_year":2018,"status":"A01","sr_id":"sr:player:1473928","draft":{"year":2018,"round":3,"number":79,"team":{"id":"3d08af9e-c767-4f88-a7dc-b920c6d2b4a8","name":"Seahawks","market":"Seattle","alias":"SEA","sr_id":"sr:competitor:4430"}},"references":[{"id":"00-0034831","origin":"gsis"},{"id":"46148","origin":"nflx"}]},{"id":"9d546e3b-0eb3-4926-a5ef-eb5e48b9330e","name":"L.J. Collier","jersey":"91","last_name":"Collier","first_name":"L.J.","abbr_name":"L.Collier","preferred_name":"L.J.","birth_date":"1995-09-12","weight":291.0,"height":74,"position":"DE","birth_place":"Munday, TX, USA","high_school":"Munday (TX)","college":"Texas Christian","college_conf":"Big Twelve Conference","rookie_year":2019,"status":"A01","sr_id":"sr:player:1220106","draft":{"year":2019,"round":1,"number":29,"team":{"id":"3d08af9e-c767-4f88-a7dc-b920c6d2b4a8","name":"Seahawks","market":"Seattle","alias":"SEA","sr_id":"sr:competitor:4430"}},"references":[{"id":"00-0035636","origin":"gsis"},{"id":"47812","origin":"nflx"}]},{"id":"a296f2fe-7af8-4796-b50a-28ef010d0933","name":"Penny Hart","jersey":"19","last_name":"Hart","first_name":"Penny","abbr_name":"P.Hart","preferred_name":"Penny","birth_date":"1996-07-05","weight":180.0,"height":68,"position":"WR","birth_place":"Roswell, GA, USA","high_school":"King's Ridge Christian (GA)","college":"Georgia State","college_conf":"Sun Belt Conference","rookie_year":2019,"status":"A01","sr_id":"sr:player:1211410","references":[{"id":"00-0035022","origin":"gsis"},{"id":"48119","origin":"nflx"}]},{"id":"a2b2f929-e3a7-4d19-888f-49600cf718bf","name":"Brandon Shell","jersey":"72","last_name":"Shell","first_name":"Brandon","abbr_name":"B.Shell","preferred_name":"Brandon","birth_date":"1992-02-06","weight":324.0,"height":77,"position":"T","birth_place":"Goose Creek, SC, USA","high_school":"Goose Creek (SC)","college":"South Carolina","college_conf":"Southeastern Conference","rookie_year":2016,"status":"A01","sr_id":"sr:player:988729","draft":{"year":2016,"round":5,"number":158,"team":{"id":"5fee86ae-74ab-4bdd-8416-42a9dd9964f3","name":"Jets","market":"New York","alias":"NYJ","sr_id":"sr:competitor:4427"}},"references":[{"id":"43447","origin":"nflx"},{"id":"00-0032420","origin":"gsis"}]},{"id":"aaf9cdda-8da8-4b3d-95bf-6fea8070a537","name":"Gavin Heslop","jersey":"38","last_name":"Heslop","first_name":"Gavin","abbr_name":"G.Heslop","preferred_name":"Gavin","birth_date":"1997-11-13","weight":200.0,"height":73,"position":"DB","birth_place":"Yonkers, NY, USA","high_school":"Archbishop Stepinac (NY)","college":"Stony Brook","college_conf":"Colonial Athletic Association","rookie_year":2020,"status":"A01","sr_id":"sr:player:1227964","references":[{"id":"00-0036056","origin":"gsis"},{"id":"52959","origin":"nflx"}]},{"id":"ad2a1d03-020b-487a-bd5f-7ca9fbc250fe","name":"Jacob Hollister","jersey":"86","last_name":"Hollister","first_name":"Jacob","abbr_name":"J.Hollister","preferred_name":"Jacob","birth_date":"1993-11-18","weight":245.0,"height":76,"position":"TE","birth_place":"Bend, OR, USA","high_school":"Mountain View (OR)","college":"Wyoming","college_conf":"Mountain West Conference","rookie_year":2017,"status":"A01","sr_id":"sr:player:1130477","references":[{"id":"45281","origin":"nflx"},{"id":"00-0033387","origin":"gsis"}]},{"id":"aecc1809-4628-4c3a-8b2b-c8f2858d2492","name":"David Moore","jersey":"83","last_name":"Moore","first_name":"David","abbr_name":"D.Moore","preferred_name":"David","birth_date":"1995-01-15","weight":215.0,"height":72,"position":"WR","birth_place":"Gainesville, TX, USA","high_school":"Gainesville (TX)","college":"East Central","college_conf":"Great American Conference","rookie_year":2017,"status":"A01","sr_id":"sr:player:1130169","draft":{"year":2017,"round":7,"number":226,"team":{"id":"3d08af9e-c767-4f88-a7dc-b920c6d2b4a8","name":"Seahawks","market":"Seattle","alias":"SEA","sr_id":"sr:competitor:4430"}},"references":[{"id":"00-0033589","origin":"gsis"},{"id":"45039","origin":"nflx"}]},{"id":"b2805ba0-6faa-404d-b0b5-7c8ccce85f3a","name":"Cedric Ogbuehi","jersey":"74","last_name":"Ogbuehi","first_name":"Cedric","abbr_name":"C.Ogbuehi","preferred_name":"Cedric","birth_date":"1992-04-25","weight":310.0,"height":77,"position":"T","birth_place":"Allen, TX, USA","high_school":"Allen (TX)","college":"Texas A&amp;M","college_conf":"Southeastern Conference","rookie_year":2015,"status":"A01","sr_id":"sr:player:834529","draft":{"year":2015,"round":1,"number":21,"team":{"id":"ad4ae08f-d808-42d5-a1e6-e9bc4e34d123","name":"Bengals","market":"Cincinnati","alias":"CIN","sr_id":"sr:competitor:4416"}},"references":[{"id":"00-0032233","origin":"gsis"},{"id":"42364","origin":"nflx"}]},{"id":"b47fe0b2-e002-42a7-ab84-4b9e61adc9e3","name":"Alex McGough","jersey":"3","last_name":"McGough","first_name":"Alex","abbr_name":"A.McGough","preferred_name":"Alex","birth_date":"1995-11-19","weight":214.0,"height":75,"position":"QB","birth_place":"Tampa, FL, USA","high_school":"Gaither (FL)","college":"Florida International","college_conf":"Conference USA","rookie_year":2018,"status":"A01","sr_id":"sr:player:1524051","draft":{"year":2018,"round":7,"number":220,"team":{"id":"3d08af9e-c767-4f88-a7dc-b920c6d2b4a8","name":"Seahawks","market":"Seattle","alias":"SEA","sr_id":"sr:competitor:4430"}},"references":[{"id":"46289","origin":"nflx"},{"id":"00-0034732","origin":"gsis"}]},{"id":"b612c556-1285-405f-9294-733f0302869e","name":"Benson Mayowa","jersey":"95","last_name":"Mayowa","first_name":"Benson","abbr_name":"B.Mayowa","preferred_name":"Benson","birth_date":"1991-08-03","weight":265.0,"height":75,"position":"DE","birth_place":"Inglewood, CA, USA","high_school":"Inglewood (CA)","college":"Idaho","college_conf":"Western Athletic Conference","rookie_year":2013,"status":"A01","sr_id":"sr:player:829237","references":[{"id":"00-0030380","origin":"gsis"},{"id":"40825","origin":"nflx"}]},{"id":"b7b3c187-7447-4d02-94b7-5d3ee64ca530","name":"Neiko Thorpe","jersey":"23","last_name":"Thorpe","first_name":"Neiko","abbr_name":"N.Thorpe","preferred_name":"Neiko","birth_date":"1990-02-01","weight":210.0,"height":74,"position":"CB","birth_place":"Southfield, MI, USA","high_school":"Tucker (GA)","college":"Auburn","college_conf":"Southeastern Conference","rookie_year":2012,"status":"A01","sr_id":"sr:player:827639","references":[{"id":"00-0029329","origin":"gsis"},{"id":"39232","origin":"nflx"}]},{"id":"b9e6500f-2bb4-47b1-a3ea-1e3f925a3743","name":"Damarious Randall","jersey":"36","last_name":"Randall","first_name":"Damarious","abbr_name":"D.Randall","preferred_name":"Damarious","birth_date":"1992-08-29","weight":196.0,"height":71,"position":"FS","birth_place":"Pensacola, FL, USA","high_school":"Pensacola (FL)","college":"Arizona State","college_conf":"Pacific Twelve Conference","rookie_year":2015,"status":"A01","sr_id":"sr:player:834555","draft":{"year":2015,"round":1,"number":30,"team":{"id":"a20471b4-a8d9-40c7-95ad-90cc30e46932","name":"Packers","market":"Green Bay","alias":"GB","sr_id":"sr:competitor:4420"}},"references":[{"id":"00-0032251","origin":"gsis"},{"id":"42373","origin":"nflx"}]},{"id":"bad1a0c1-7ea2-4898-b5d9-ad1aec45c8b1","name":"Tyler Mabry","jersey":"85","last_name":"Mabry","first_name":"Tyler","abbr_name":"T.Mabry","preferred_name":"Tyler","birth_date":"1996-11-21","weight":248.0,"height":76,"position":"TE","birth_place":"Ypsilanti, MI, USA","high_school":"IMG Academy (FL)","college":"Maryland","college_conf":"Big Ten Conference","rookie_year":2020,"status":"A01","sr_id":"sr:player:1191446","references":[{"id":"52962","origin":"nflx"},{"id":"00-0036059","origin":"gsis"}]},{"id":"bdeffac7-3509-4689-af1b-29e9fe86b008","name":"Jayson Stanley","jersey":"39","last_name":"Stanley","first_name":"Jayson","abbr_name":"J.Stanley","preferred_name":"Jayson","birth_date":"1997-04-24","weight":207.0,"height":74,"position":"CB","birth_place":"Fairburn, GA, USA","high_school":"Creekside (GA)","college":"Georgia","college_conf":"Southeastern Conference","rookie_year":2019,"status":"A01","sr_id":"sr:player:1188266","references":[{"id":"00-0035207","origin":"gsis"},{"id":"48373","origin":"nflx"}]},{"id":"c00e0b6f-367f-4cf5-ba11-d23b1aa114f1","name":"John Ursua","jersey":"15","last_name":"Ursua","first_name":"John","abbr_name":"J.Ursua","preferred_name":"John","birth_date":"1994-01-17","weight":182.0,"height":69,"position":"WR","birth_place":"La'ie, HI, USA","high_school":"Cedar City (UT)","college":"Hawaii","college_conf":"Mountain West Conference","rookie_year":2019,"status":"A01","sr_id":"sr:player:1769148","draft":{"year":2019,"round":7,"number":236,"team":{"id":"3d08af9e-c767-4f88-a7dc-b920c6d2b4a8","name":"Seahawks","market":"Seattle","alias":"SEA","sr_id":"sr:competitor:4430"}},"references":[{"id":"00-0035597","origin":"gsis"},{"id":"48019","origin":"nflx"}]},{"id":"c02b49d3-ddc1-4ffc-9f40-487199882fa5","name":"Jarran Reed","jersey":"90","last_name":"Reed","first_name":"Jarran","abbr_name":"J.Reed","preferred_name":"Jarran","birth_date":"1992-12-16","weight":306.0,"height":75,"position":"DT","birth_place":"Goldsboro, NC, USA","high_school":"Goldsboro (NC)","college":"Alabama","college_conf":"Southeastern Conference","rookie_year":2016,"status":"A01","sr_id":"sr:player:1074138","draft":{"year":2016,"round":2,"number":49,"team":{"id":"3d08af9e-c767-4f88-a7dc-b920c6d2b4a8","name":"Seahawks","market":"Seattle","alias":"SEA","sr_id":"sr:competitor:4430"}},"references":[{"id":"43338","origin":"nflx"},{"id":"00-0032387","origin":"gsis"}]},{"id":"c5614795-d8e3-4104-ad9b-edfb575410bb","name":"Jordan Miller","jersey":"28","last_name":"Miller","first_name":"Jordan","abbr_name":"J.Miller","preferred_name":"Jordan","birth_date":"1997-02-08","weight":190.0,"height":74,"position":"CB","birth_place":"Oceanside, CA, USA","high_school":"Oceanside (CA)","college":"Washington","college_conf":"Pacific Twelve Conference","rookie_year":2019,"status":"A01","sr_id":"sr:player:1222484","draft":{"year":2019,"round":5,"number":172,"team":{"id":"e6aa13a4-0055-48a9-bc41-be28dc106929","name":"Falcons","market":"Atlanta","alias":"ATL","sr_id":"sr:competitor:4393"}},"references":[{"id":"47955","origin":"nflx"},{"id":"00-0035285","origin":"gsis"}]},{"id":"c682e8ea-fe48-45d2-af60-682a6125ab22","name":"Phillip Dorsett II","jersey":"11","last_name":"Dorsett","first_name":"Phillip","abbr_name":"P.Dorsett II","preferred_name":"Phillip","birth_date":"1993-01-05","weight":192.0,"height":70,"position":"WR","birth_place":"Fort Lauderdale, FL, USA","high_school":"St. Thomas Aquinas (FL)","college":"Miami","college_conf":"Atlantic Coast Conference","rookie_year":2015,"status":"A01","sr_id":"sr:player:834499","name_suffix":"II","draft":{"year":2015,"round":1,"number":29,"team":{"id":"82cf9565-6eb9-4f01-bdbd-5aa0d472fcd9","name":"Colts","market":"Indianapolis","alias":"IND","sr_id":"sr:competitor:4421"}},"references":[{"id":"00-0032208","origin":"gsis"},{"id":"42372","origin":"nflx"}]},{"id":"c7e51d4d-18d6-442b-850d-040411225b14","name":"Tyler Ott","jersey":"69","last_name":"Ott","first_name":"Tyler","abbr_name":"T.Ott","preferred_name":"Tyler","birth_date":"1992-02-28","weight":253.0,"height":75,"position":"LS","birth_place":"Tulsa, OK, USA","high_school":"Jenks (OK)","college":"Harvard","college_conf":"Ivy League","rookie_year":2014,"status":"A01","sr_id":"sr:player:855138","references":[{"id":"00-0031156","origin":"gsis"},{"id":"41973","origin":"nflx"}]},{"id":"c99cb557-3364-4755-a353-82737ba1de6b","name":"Darvin Kidsy","jersey":"84","last_name":"Kidsy","first_name":"Darvin","abbr_name":"D.Kidsy","preferred_name":"Darvin","birth_date":"1995-03-19","weight":180.0,"height":72,"position":"WR","birth_place":"Missouri City, TX, USA","high_school":"Elkins (TX)","college":"Texas Southern","college_conf":"Southwestern Athletic Conference","rookie_year":2018,"status":"A01","sr_id":"sr:player:1272102","name_suffix":"Jr.","references":[{"id":"00-0034710","origin":"gsis"},{"id":"46891","origin":"nflx"}]},{"id":"ccfcbd2c-6e35-49b9-b131-ba2143665260","name":"Jonathan Bullard","jersey":"93","last_name":"Bullard","first_name":"Jonathan","abbr_name":"J.Bullard","preferred_name":"Jonathan","birth_date":"1993-10-22","weight":296.0,"height":75,"position":"DE","birth_place":"Shelby, NC, USA","high_school":"Crest (NC)","college":"Florida","college_conf":"Southeastern Conference","rookie_year":2016,"status":"A01","sr_id":"sr:player:1073936","draft":{"year":2016,"round":3,"number":72,"team":{"id":"7b112545-38e6-483c-a55c-96cf6ee49cb8","name":"Bears","market":"Chicago","alias":"CHI","sr_id":"sr:competitor:4391"}},"references":[{"id":"43361","origin":"nflx"},{"id":"00-0033093","origin":"gsis"}]},{"id":"cfc93f5e-105e-4a5e-88d3-f4279893cfa8","name":"Geno Smith","jersey":"7","last_name":"Smith","first_name":"Geno","abbr_name":"G.Smith","preferred_name":"Geno","birth_date":"1990-10-10","weight":221.0,"height":75,"position":"QB","birth_place":"Miramar, FL, USA","high_school":"Miramar (FL)","college":"West Virginia","college_conf":"Big Twelve Conference","rookie_year":2013,"status":"A01","sr_id":"sr:player:830531","draft":{"year":2013,"round":2,"number":39,"team":{"id":"5fee86ae-74ab-4bdd-8416-42a9dd9964f3","name":"Jets","market":"New York","alias":"NYJ","sr_id":"sr:competitor:4427"}},"references":[{"id":"00-0030565","origin":"gsis"},{"id":"39987","origin":"nflx"}]},{"id":"d1ae3222-8892-49bc-bb3e-0bcd7c74522e","name":"Michael Dickson","jersey":"4","last_name":"Dickson","first_name":"Michael","abbr_name":"M.Dickson","preferred_name":"Michael","birth_date":"1996-01-04","weight":208.0,"height":74,"position":"P","birth_place":"Sydney,, AUS","high_school":"Kirrawee (AUS)","college":"Texas","college_conf":"Big Twelve Conference","rookie_year":2018,"status":"A01","sr_id":"sr:player:1222324","draft":{"year":2018,"round":5,"number":149,"team":{"id":"3d08af9e-c767-4f88-a7dc-b920c6d2b4a8","name":"Seahawks","market":"Seattle","alias":"SEA","sr_id":"sr:competitor:4430"}},"references":[{"id":"46218","origin":"nflx"},{"id":"00-0034160","origin":"gsis"}]},{"id":"d5fde14a-1f7e-4db7-ad67-e6ea1cd415e2","name":"Lano Hill","jersey":"42","last_name":"Hill","first_name":"Delano","abbr_name":"L.Hill","preferred_name":"Delano","birth_date":"1995-11-26","weight":216.0,"height":73,"position":"SS","birth_place":"Detroit, MI, USA","high_school":"Cass Tech (MI)","college":"Michigan","college_conf":"Big Ten Conference","rookie_year":2017,"status":"A01","sr_id":"sr:player:1129865","draft":{"year":2017,"round":3,"number":95,"team":{"id":"3d08af9e-c767-4f88-a7dc-b920c6d2b4a8","name":"Seahawks","market":"Seattle","alias":"SEA","sr_id":"sr:competitor:4430"}},"references":[{"id":"44907","origin":"nflx"},{"id":"00-0033931","origin":"gsis"}]},{"id":"dd7640e6-d81d-4605-b900-451bf40e5bd6","name":"Shaquill Griffin","jersey":"26","last_name":"Griffin","first_name":"Shaquill","abbr_name":"S.Griffin","preferred_name":"Shaquill","birth_date":"1995-07-20","weight":198.0,"height":72,"position":"CB","birth_place":"St. Petersburg, FL, USA","high_school":"Lakewood (FL)","college":"Central Florida","college_conf":"American Athletic Conference","rookie_year":2017,"status":"A01","sr_id":"sr:player:1129823","draft":{"year":2017,"round":3,"number":90,"team":{"id":"3d08af9e-c767-4f88-a7dc-b920c6d2b4a8","name":"Seahawks","market":"Seattle","alias":"SEA","sr_id":"sr:competitor:4430"}},"references":[{"id":"00-0033926","origin":"gsis"},{"id":"44902","origin":"nflx"}]},{"id":"df2caa7b-29f4-4391-8ce0-b1b711196379","name":"Aaron Fuller","jersey":"17","last_name":"Fuller","first_name":"Aaron","abbr_name":"A.Fuller","preferred_name":"Aaron","birth_date":"1997-09-30","weight":188.0,"height":71,"position":"WR","birth_place":"McKinney, TX, USA","high_school":"Lovejoy (TX)","college":"Washington","college_conf":"Pacific Twelve Conference","rookie_year":2020,"status":"A01","sr_id":"sr:player:1221532","references":[{"id":"00-0035987","origin":"gsis"},{"id":"52889","origin":"nflx"}]},{"id":"dffa69ad-331e-4f09-ae38-40a5a4406be6","name":"Tyler Lockett","jersey":"16","last_name":"Lockett","first_name":"Tyler","abbr_name":"T.Lockett","preferred_name":"Tyler","birth_date":"1992-09-28","weight":182.0,"height":70,"position":"WR","birth_place":"Tulsa, OK, USA","high_school":"Booker T. Washington (OK)","college":"Kansas State","college_conf":"Big Twelve Conference","rookie_year":2015,"status":"A01","sr_id":"sr:player:834657","draft":{"year":2015,"round":3,"number":69,"team":{"id":"3d08af9e-c767-4f88-a7dc-b920c6d2b4a8","name":"Seahawks","market":"Seattle","alias":"SEA","sr_id":"sr:competitor:4430"}},"references":[{"id":"42412","origin":"nflx"},{"id":"00-0032211","origin":"gsis"}]},{"id":"e2104140-4ce0-42a8-8b00-346b4a9258b2","name":"Danny Etling","jersey":"2","last_name":"Etling","first_name":"Danny","abbr_name":"D.Etling","preferred_name":"Danny","birth_date":"1994-07-22","weight":220.0,"height":75,"position":"QB","birth_place":"Terre Haute, IN, USA","high_school":"South Vigo (IN)","college":"Louisiana State","college_conf":"Southeastern Conference","rookie_year":2018,"status":"A01","sr_id":"sr:player:1524109","draft":{"year":2018,"round":7,"number":219,"team":{"id":"97354895-8c77-4fd4-a860-32e62ea7382a","name":"Patriots","market":"New England","alias":"NE","sr_id":"sr:competitor:4424"}},"references":[{"id":"46288","origin":"nflx"},{"id":"00-0034423","origin":"gsis"}]},{"id":"e6d6138f-1081-457b-9d89-dc9cd0ab9598","name":"Myles Adams","jersey":"79","last_name":"Adams","first_name":"Myles","abbr_name":"M.Adams","preferred_name":"Myles","birth_date":"1998-03-09","weight":285.0,"height":74,"position":"DT","birth_place":"Arlington, TX, USA","high_school":"Mansfield Summit (TX)","college":"Rice","college_conf":"Conference USA","rookie_year":2020,"status":"A01","sr_id":"sr:player:1183368","references":[{"id":"00-0035946","origin":"gsis"},{"id":"52848","origin":"nflx"}]},{"id":"e79d8a12-4ec0-46d3-ae42-384f16deebed","name":"Carlos Dunlap","jersey":"43","last_name":"Dunlap","first_name":"Carlos","abbr_name":"C.Dunlap","preferred_name":"Carlos","birth_date":"1989-02-28","weight":285.0,"height":78,"position":"DE","birth_place":"North Charleston, SC, USA","high_school":"Fort Dorchester (SC)","college":"Florida","college_conf":"Southeastern Conference","rookie_year":2010,"status":"A01","sr_id":"sr:player:828889","draft":{"year":2010,"round":2,"number":54,"team":{"id":"ad4ae08f-d808-42d5-a1e6-e9bc4e34d123","name":"Bengals","market":"Cincinnati","alias":"CIN","sr_id":"sr:competitor:4416"}},"references":[{"id":"00-0027662","origin":"gsis"},{"id":"35493","origin":"nflx"}]},{"id":"eeb9e3f4-e378-44ca-94b6-a724011ad710","name":"Nick Bellore","jersey":"44","last_name":"Bellore","first_name":"Nick","abbr_name":"N.Bellore","preferred_name":"Nick","birth_date":"1989-05-12","weight":250.0,"height":73,"position":"FB","birth_place":"St. Paul, MN, USA","high_school":"Whitefish Bay (WI)","college":"Central Michigan","college_conf":"Mid-American Conference","rookie_year":2011,"status":"A01","sr_id":"sr:player:828461","references":[{"id":"37792","origin":"nflx"},{"id":"00-0028292","origin":"gsis"}]},{"id":"ef422c88-b74f-4720-a831-947010c44ebe","name":"Jordyn Brooks","jersey":"56","last_name":"Brooks","first_name":"Jordyn","abbr_name":"J.Brooks","preferred_name":"Jordyn","birth_date":"1997-10-21","weight":245.0,"height":73,"position":"OLB","birth_place":"Houston, TX, USA","high_school":"Stratford (TX)","college":"Texas Tech","college_conf":"Big Twelve Conference","rookie_year":2020,"status":"A01","sr_id":"sr:player:2040011","draft":{"year":2020,"round":1,"number":27,"team":{"id":"3d08af9e-c767-4f88-a7dc-b920c6d2b4a8","name":"Seahawks","market":"Seattle","alias":"SEA","sr_id":"sr:competitor:4430"}},"references":[{"id":"52435","origin":"nflx"},{"id":"00-0036409","origin":"gsis"}]},{"id":"f00ccf29-884e-4914-b9f9-aca0090ee9e6","name":"Bryan Mone","jersey":"92","last_name":"Mone","first_name":"Bryan","abbr_name":"B.Mone","preferred_name":"Bryan","birth_date":"1995-10-20","weight":366.0,"height":75,"position":"NT","birth_place":"Salt Lake City, UT, USA","high_school":"Highland (UT)","college":"Michigan","college_conf":"Big Ten Conference","rookie_year":2019,"status":"A01","sr_id":"sr:player:1737585","references":[{"id":"48198","origin":"nflx"},{"id":"00-0035094","origin":"gsis"}]},{"id":"f26bd260-a1eb-42ab-8768-bc8ad24e4f9e","name":"Duane Brown","jersey":"76","last_name":"Brown","first_name":"Duane","abbr_name":"D.Brown","preferred_name":"Duane","birth_date":"1985-08-30","weight":315.0,"height":76,"position":"T","birth_place":"Richmond, VA, USA","high_school":"Hermitage (VA)","college":"Virginia Tech","college_conf":"Atlantic Coast Conference","rookie_year":2008,"status":"A01","sr_id":"sr:player:828997","draft":{"year":2008,"round":1,"number":26,"team":{"id":"82d2d380-3834-4938-835f-aec541e5ece7","name":"Texans","market":"Houston","alias":"HOU","sr_id":"sr:competitor:4324"}},"references":[{"id":"00-0026166","origin":"gsis"},{"id":"33107","origin":"nflx"}]},{"id":"fc116de9-ceb8-409b-b322-60659c73e943","name":"Alton Robinson","jersey":"98","last_name":"Robinson","first_name":"Alton","abbr_name":"A.Robinson","preferred_name":"Alton","birth_date":"1998-06-02","weight":260.0,"height":76,"position":"DE","birth_place":"Converse, TX, USA","high_school":"Judson (TX)","college":"Syracuse","college_conf":"Atlantic Coast Conference","rookie_year":2020,"status":"A01","sr_id":"sr:player:1270352","draft":{"year":2020,"round":5,"number":148,"team":{"id":"3d08af9e-c767-4f88-a7dc-b920c6d2b4a8","name":"Seahawks","market":"Seattle","alias":"SEA","sr_id":"sr:competitor:4430"}},"references":[{"id":"52556","origin":"nflx"},{"id":"00-0036426","origin":"gsis"}]}],"_comment":"Generation started @ 2021-02-12 18:03:25 UTC ended @ 2021-02-12 18:03:25 UTC"}